{"title":"Combined feed","url":"https://MOVIECORD.github.io/entertain.daum/all.xml","elements":[{"title":"‘대배우’ 송강호, 8번째 칸 출장‥오늘 프랑스로 출국 (다음 연예 ─ 뉴스 ─ 영화)","contents":"[뉴스엔 배효주 기자] '거미집'이 제76회 칸 국제영화제를 통해 공개되는 가운데, 송강호가 프랑스 행 비행기에 몸을 실었다. 영화 '거미집'(감독 김지운)은 1970년대, 다 찍은 영화 ‘거미집’의 결말만 다시 찍으면 걸작이 될 거라 믿는 김감독이 검열, 바뀐 내용을 이해하지 못하는 배우와 제작자 등 미치기 일보 직전의 악조건 속에서 촬영을 밀어붙이며","link":"https://v.daum.net/v/20230522190930415","retrieved":1684750304781},{"title":"\"행복했다\"..'멜로킹' 김선호가 보여줄 새로운 광인의 얼굴 (다음 연예 ─ 뉴스 ─ 영화)","contents":"[스타뉴스 | 김미화 기자] 배우 김선호가 22일 오전 서울 광진구 롯데시네마 건대입구에서 진행된 영화 '귀공자' 제작보고회에 참석해 미소를 짓고 있다.  '귀공자'는 필리핀 불법 경기장을 전전하는 복싱 선수 '마르코' 앞에 정체불명의 남자 '귀공자'를 비롯한 각기 다른 목적을 지닌 세력들이 나타나 광기의 추격을 펼치는 이야기. 내달 21일 개봉. 2023","link":"https://v.daum.net/v/20230522190001159","retrieved":1684750304784},{"title":"오드리 햅번→톰 크루즈..디즈니 캐릭터 얼굴에 영감 준 배우들 '도플갱어' (다음 연예 ─ 뉴스 ─ 영화)","contents":"[OSEN=최나영 기자] '디즈니 도플갱어!' 배우 알리사 밀라노부터 톰 크루즈까지. 애니메이션&nbsp;캐릭터들의 얼굴에 영감을 준 연예인들이 있다. 디즈니 주인공들의&nbsp;비주얼이 많은 부분&nbsp;실제 유명인사들로부터 영감을 받았다는 것이 밝혀졌다. 오드리 햅번과 엘리자베스 테일러,&nbsp;톰 크루즈와 제레미 아이언스에 이르기까지, 할리우드의 유명&nbsp;배우들이 전 세계 어린이들과","link":"https://v.daum.net/v/20230522185019937","retrieved":1684750304784},{"title":"이준혁 \"마동석에게 맞고 싶었다\"…'범죄도시3'로 변화한 삶 (다음 연예 ─ 뉴스 ─ 영화)","contents":"(엑스포츠뉴스 윤현지 기자) 배우 이준혁이 '범죄도시3'에서 새로운 얼굴을 선보였다. 22일 오후 서울 강남구 메가박스 코엑스에서 영화 '범죄도시3'(감독 이상용) 언론배급시사회가 열렸다. 현장에는 이상용 감독과 배우 마동석, 이준혁, 아오키 무네타카가 참석했다. '범죄도시3'는 대체불가 괴물형사 마석도(마동석 분)가 서울 광수대로 이동 후, 신종 마약 범","link":"https://v.daum.net/v/20230522185007923","retrieved":1684750304787},{"title":"'멜로 장인' 김선호-1,980:1의 사나이 강태주, '귀공자'로 스크린 출격 (다음 연예 ─ 뉴스 ─ 영화)","contents":"(MHN스포츠 정승민 인턴기자) 멜로 장인에서 광기 넘치는 추격자로 변신한 김선호와 1,980:1의 경쟁률을 뚫은 신예 강태주가 '귀공자'를 통해 스크린에 데뷔한다. 22일 오전 서울 광진구 롯데시네마 건대입구에서 영화 '귀공자' 제작보고회가 열렸다. 이날은 박훈정 감독, 김선호, 강태주, 김강우, 고아라가 참석했으며 진행은 방송인 박경림이 맡았다","link":"https://v.daum.net/v/20230522183004544","retrieved":1684750304789},{"title":"칸에서 기립박수 받은 ‘탈출’, “영화제 기간 중 가장 빨리 순삭한 100분” (다음 연예 ─ 뉴스 ─ 영화)","contents":"[스포츠서울 | 조은별기자]배우 이선균·주지훈 주연 영화 ‘탈출:프로젝트 사일런스’(ROJECT SILENCE, 이하 ‘탈출’ )가 칸 국제영화제에서 기립박수를 받았다. 제 76회 칸국제영화제 비경쟁부문 ‘미드나잇 스크리닝’에 공식초청된 ‘탈출’은 21일 밤 12시 30분(이하 현지시간) 뤼미에르 대극장에서 처음으로 상영됐다. ‘미드나잇 스크리닝’은","link":"https://v.daum.net/v/20230522181216181","retrieved":1684750304790},{"title":"쫓는 피해자와 쫓기는 가해자, 시골 마을의 비극 (다음 연예 ─ 뉴스 ─ 영화)","contents":"[김형욱 기자] &nbsp;▲ &nbsp;넷플릭스 오리지널 영화 &lt;질식&gt; 포스터.ⓒ 넷플릭스&nbsp; 튀르키예 이스탄불에서 투자 회사를 크게 운영하다가, 사기와 횡령 등의 혐의로 감옥에 갔다가 출소 후 재판을 받고 있는&nbsp;얄른은&nbsp;아내 베이가와 함께 에게해의 작은 시골에 온다. 그들 딴에는 새롭게 다시 시작해 보자는 의미라지만, 실상은 사람들 눈을 피해 도망치듯 온 것이리라. 하지만","link":"https://v.daum.net/v/20230522180925107","retrieved":1684746678741},{"title":"아무도 모르는 '우뢰매'의 진짜 흥행성적 (다음 연예 ─ 뉴스 ─ 영화)","contents":"[양형석 기자] 제작사 입장에서는 특정 영화가 시리즈 물로 가능성을 보이면 영원히 그 시리즈를 유지하고 싶겠지만 관객들은 시리즈 영화가 큰 변화 없이 이어지면 더 이상 그 프랜차이즈에 관심을 두지 않는다. 따라서 최근에는 기획 단계부터 3부작, 길어도 4부작을 넘어가지 않게 시리즈 영화를 구상하는 경우가 많다. 대신 &lt;배트맨&gt;이나 &lt;스파이더맨&gt;처럼 캐릭터의","link":"https://v.daum.net/v/20230522175701712","retrieved":1684746678749},{"title":"'범죄도시3' 마동석, 혼을 갈아 넣었다 \"무릎 연골 없는 채로 액션\" (다음 연예 ─ 뉴스 ─ 영화)","contents":"아이즈 ize 김나라 기자배우 마동석이 '범죄도시3'에 혼을 갈아 넣은 열연으로 올여름 극장가에 강력한 한 방을 투척한다.'범죄도시3'(감독 이상용)는 침체기에 빠진 한국 영화를 구원할 희망으로&nbsp;꼽히는 올여름 최고 기대작. 2017년 1편으로 688만 명을 동원하며 역대 청소년 관람불가 흥행 톱3 기록을 세우고, 작년 2편으론 무려 1,269만 명을 모으며","link":"https://v.daum.net/v/20230522175700709","retrieved":1684746678752},{"title":"'2TOP 빌런'과 함께 강해진 마동석의 핵주먹, '범죄도시3' (다음 연예 ─ 뉴스 ─ 영화)","contents":"\"시리즈 계속 하고파\"...'범죄도시'에 담은 마동석의 자신감, 31일 개봉 [더팩트｜박지윤 기자] 배우 마동석이 이준혁, 아오키 무네타카와 함께 돌아왔다. 시리즈 최초 '2TOP 빌런'을 내세운 '범죄도시3'가 더 유쾌하고 통쾌한 액션과 웃음으로 극장가를 접수할 준비를 마쳤다. '범죄도시3'(감독 이상용)의 언론 시사회 및 제작보고회가 22일 오후 서","link":"https://v.daum.net/v/20230522175634704","retrieved":1684746678752},{"title":"이선균·주지훈·김희원 ‘탈출’, 칸 영화제서 기립 박수 받았다 (다음 연예 ─ 뉴스 ─ 영화)","contents":"제76회 칸 국제영화제 비경쟁부문 ‘미드나잇 스크리닝’ 공식 초청작 ‘탈출: PROJECT SILENCE’가 기립 박수를 받았다. 프랑스 현지 시각으로 지난 21일(일) 밤 12시 30분(한국시간 22일 7시 30분) 제76회 칸 국제영화제에 초청받은 ‘탈출: PROJECT SILENCE’가 영화제 메인 상영관인 뤼미에르 대극장에서 세계 최초로 상영됐다.","link":"https://v.daum.net/v/20230522175106593","retrieved":1684746678753},{"title":"\"빌런, 외모가 1순위\"...윤계상 손석구 그리고 이준혁, 빌런 계보 (다음 연예 ─ 뉴스 ─ 영화)","contents":"(엑스포츠뉴스 김유진 기자) 세 번째 시리즈를 맞은 '범죄도시3'를 연출한 이상용 감독이 1편부터 꾸준히 주목 받고 있는 빌런들의 존재감을 언급했다. 22일 서울 강남구 메가박스 코엑스에서 영화 '범죄도시3'(감독 이상용) 언론시사회가 열렸다. 이 자리에는 이상용 감독과 배우 마동석, 이준혁, 아오키 무네타카가 참석했다. '범죄도시3'는 대체불가 괴물형사","link":"https://v.daum.net/v/20230522175008562","retrieved":1684746678754},{"title":"'탈출: PROJECT SILENCE' 칸 상영…이선균·주지훈·김희원, 환호 속 뜨거운 포옹 (다음 연예 ─ 뉴스 ─ 영화)","contents":"(엑스포츠뉴스 김유진 기자) 제76회 칸국제영화제 비경쟁부문 미드나잇 스크리닝 공식 초청작 영화 '탈출: PROJECT SILENCE'(감독 김태곤)가 프랑스 칸 현지에서 세계 최초로 상영을 마쳤다. 프랑스 현지 시각으로 지난 21일 밤 12시 30분(한국시간 22일 오전 7시 30분) 제76회 칸국제영화제에 초청받은 '탈출: PROJECT SILENCE'","link":"https://v.daum.net/v/20230522174711481","retrieved":1684746678757},{"title":"블랙핑크 제니 뜬다…첫 연기 도전작 '더 아이돌' 오늘 공개 (다음 연예 ─ 뉴스 ─ 영화)","contents":"(칸=뉴스1) 고승아 기자 = 그룹 블랙핑크 제니의 첫 연기 도전작으로 화제를 모은 '더 아이돌'이 드디어 베일을 벗는다. 22일 오후 10시30분(현지시간, 한국시간 23일 오전 5시30분) 프랑스 남부 칸 팔레 데 페스티발 뤼미에르 대극장에서 HBO '더 아이돌'(The Idol)이 월드 프리미어로 상영된다. 올해 칸 영화제 비경쟁 부문에 초청을 받","link":"https://v.daum.net/v/20230522173834203","retrieved":1684746678761},{"title":"'사생활 논란' 김선호, 스크린 데뷔작 '귀공자'로 여론 돌릴까 (다음 연예 ─ 뉴스 ─ 영화)","contents":"[티브이데일리 최하나 기자] 배우 김선호가 ‘귀공자’로 첫 스크린 데뷔 무대에 섰다. 더불어 사생활 논란으로 돌아선 여론까지 잡아야하는 시험대에 오른 김선호다. 22일 오전 서울시 광진구 자양동에 위치한 롯데시네마 건대입구에서 진행된 영화 ’귀공자‘(감독 박훈정) 제작보고회에서는 박훈정 감독을 비롯해 출연 배우 김선호 강태주 김강우 고아라 등이 참석해 다","link":"https://v.daum.net/v/20230522173806193","retrieved":1684746678762},{"title":"'장사천재 백사장' 매출 1등 목전에 두고  웃지 못한 이유는? (다음 연예 ─ 뉴스 ─ 드라마)","contents":"사진=tvN[이데일리 스타in 유준하 기자] tvN ‘장사천재 백사장’ 나폴리 유사 이래 최초의 한식당 ‘백반집’이 문전성시를 이루며 매출이 가파르게 상승했다. 매출 1위까지 바라볼 수 있을 정도였지만, ‘장사천재’ 백종원은 웃지 못했다. ‘백반집’의 체계가 무너지기 시작했고, 손님들의 불만이 속출했기 때문이었다. 지난 21일 방송된 tvN ‘장사천재 백","link":"https://v.daum.net/v/20230522182444420","retrieved":1684750310168},{"title":"사회 문제 다룬 '닥터 차정숙'...재미와 공감 모두 사로잡다 (다음 연예 ─ 뉴스 ─ 드라마)","contents":"[TV리포트=김연주 기자] JTBC '닥터 차정숙'의 재미 중 하나는 현실에서 빈번하게 일어나는 문제를 다룬다는 데 있다. 드라마 속 허구의 세계와 실제 세상이 맞닿는 묘한 쾌감이 극의 몰입도를 높인다. 지난 21일 '닥터 차정숙'에서는 차정숙(엄정화 분)이 남편 서인호(김병철 분)의 불륜에 대응하는 이야기가 전개됐다. 참다못한 차정숙은 서인호에게 이혼을","link":"https://v.daum.net/v/20230522180030844","retrieved":1684746683907},{"title":"'벌거벗은 세계사' 이혜성 \"인문학 강의 공짜 청강하는 기분\" (다음 연예 ─ 뉴스 ─ 드라마)","contents":"사진=tvN[이데일리 스타in 김가영 기자] 대한민국 대표 인문학 예능 tvN ‘벌거벗은 세계사’가 100회를 맞이한다. ‘벌거벗은 세계사(연출 김형오, 이윤호, 서용석)’는 전 세계 곳곳을 언택트로 둘러보며 각 나라의 명소를 살펴보고 다양한 관점에서 우리가 몰랐던 세계의 역사를 파헤치는 프로그램이다. 2020년 첫 선을 보인 이후, 2022년 1월 시즌","link":"https://v.daum.net/v/20230522173451113","retrieved":1684746683911},{"title":"황민현, '스터디그룹' 유쾌한 액션 주인공?..\"출연 긍정 검토 중\" (다음 연예 ─ 뉴스 ─ 드라마)","contents":"[스타뉴스 | 한해선 기자] 배우 황민현이 13일 오후 일본 나고야 니혼가이시홀에서 열린 스타뉴스-미디어보이 주최 '2022 Asia Artist Awards IN JAPAN'(2022 아시아 아티스트 어워즈, 이하 2022 AAA) 레드카펫 행사에 참석해 포즈를 취하고 있다.  스타뉴스와 미디어보이가 주최하고 Asia Artist Awards 조직위원회와","link":"https://v.daum.net/v/20230522163034898","retrieved":1684743288243},{"title":"'조선변호사' 차학연 \"정의로운 유지선 연기, 행복했다\" (다음 연예 ─ 뉴스 ─ 드라마)","contents":"[스타뉴스 | 한해선 기자] /사진=51k MBC 금토드라마 '조선변호사'에서 조선시대 최고 권력 판윤 '유지선'으로 분한 배우 차학연이 아쉬움 가득한 마지막 인사를 전했다. 지난 20일, 16회 대단원의 막을 내린 '조선변호사'(연출 김승호, 이한준 / 극본 최진영 / 제작 피플스토리컴퍼니, 원콘텐츠)에서 '유지선' 역할을 맡은 차학연이 공명정대하고 정","link":"https://v.daum.net/v/20230522160829029","retrieved":1684739533061},{"title":"임윤아, 은밀한 사생활 포착 (다음 연예 ─ 뉴스 ─ 드라마)","contents":"[마이데일리 = 박서연 기자] ‘킹더랜드’ 임윤아가 낮과 밤이 다른 일상을 공개한다. 22일 종합편성채널 JTBC 새 토일드라마 ‘킹더랜드’(극본 최롬(팀 하리마오) 연출 임현욱) 측은 고객 만족 1004%를 자랑하는 일등 친절사원 천사랑(임윤아)의 반전 매력을 한눈에 볼 수 있는 사진을 공개해 캐릭터에 대한 흥미를 돋우고 있다. 공개된 사진 속에서는","link":"https://v.daum.net/v/20230522155244369","retrieved":1684739533061},{"title":"김사부 없는 돌담병원 지킨 소주연, 정말 잘 컸다 (다음 연예 ─ 뉴스 ─ 드라마)","contents":"[뉴스엔 이민지 기자] 배우 소주연이 김사부 빈자리를 채웠다. 5월 19, 20일 방송된 SBS 금토드라마 ‘낭만닥터 김사부3’ 7, 8회에서 윤아름(소주연 분)은 김사부(한석규 분)가 잠시 자리를 비운 돌담병원 응급실을 지켜냈다. 총상환자 때문에 콜을 받은 김사부가 자리를 비운 사이, 응급실을 맡게 된 윤아름은 밀려드는 응급환자들을 프로페셔널하게 처","link":"https://v.daum.net/v/20230522153202626","retrieved":1684739533062},{"title":"류경수, 잘하는 줄은 알았는데..차원 다른 '인간美 장착 빌런' (다음 연예 ─ 뉴스 ─ 드라마)","contents":"[OSEN=최나영 기자]&nbsp;배우 류경수가 캐릭터의 다채로운 감정선을 눈빛 하나로 시청자들에게 전하며 공감까지 이끌었다. 지난&nbsp;21일 방송된&nbsp;‘구미호뎐1938’에서는 무영(류경수 분)이 이연(이동욱 분),&nbsp;홍주(김소연 분)와 옛 모습을 잠시나마 되찾는 모습이 그려졌다. 이날 무영은 이연과의 조우도 잠시 서로 검을 겨누며 팽팽한 접전을 벌였다.&nbsp;이어 홍주까지","link":"https://v.daum.net/v/20230522151843099","retrieved":1684739533062},{"title":"황민현 측 “‘스터디그룹’ 출연 긍정 검토 중” (다음 연예 ─ 뉴스 ─ 드라마)","contents":"[뉴스엔 황혜진 기자] 가수 겸 배우 황민현이 차기작을 검토하고 있다. 황민현 소속사 플레디스엔터테인먼트 측은 5월 22일 뉴스엔에 \"황민현이 '스터디그룹' 출연 제안을 받았다. 긍정 검토 중\"이라고 공식입장을 밝혔다. '스터디그룹'은 동명의 웹툰을 원작 삼아 제작되는 티빙 새 오리지널 시리즈다. 황민현이 주인공 출연을 확정, 색다른 매력의 캐릭터로 시청","link":"https://v.daum.net/v/20230522150244449","retrieved":1684736074575},{"title":"서지혜, 여관 끌려가 눈빛 돌변한 주연우에 ‘충격+공포’ (다음 연예 ─ 뉴스 ─ 드라마)","contents":"[OSEN=최나영 기자]&nbsp;‘어쩌다 마주친, 그대’의 서지혜와 주연우가 늦은 밤 우정리 마을의 여관을 방문해 충격을 안긴다. 22일(오늘) 오후&nbsp;9시 50분 방송되는 KBS 2TV 월화드라마 ‘어쩌다 마주친, 그대’(연출 강수연, 이웅희 / 극본 백소연 / 제작 아크미디어) 7회에서는 이순애(서지혜 분)가 유범룡(주연우 분)의 손에 이끌려 우정여관 앞에","link":"https://v.daum.net/v/20230522144215435","retrieved":1684736074575},{"title":"‘김사부3’ 한석규 가라사대 “아직 아무 것도 놓치지 않았어!” (다음 연예 ─ 뉴스 ─ 드라마)","contents":"[OSEN=김재동 객원기자]&nbsp;“넌 아직 아무 것도 놓치지 않았어!” 지난 20일 방송된 SBS금토드라마 ‘낭만닥터 김사부3“의 김사부(한석규 분)가 수술실에서 환자를 놓친 것으로 착각해 멘붕에 빠진 차은재(이성경 분)에게 던진 격려다. 테이블데스의 위험에 빠진 환자는 차은재가 수술전 처치를 했던 총상환자였다. 왼쪽 폐에 이어 오른쪽에도 튜브를 박으려던","link":"https://v.daum.net/v/20230522144116385","retrieved":1684736074575},{"title":"'가면의 여왕' 각성한 김선아, 더 처절해진 복수 2막 본격 돌입 (다음 연예 ─ 뉴스 ─ 드라마)","contents":"[OSEN=최나영 기자]&nbsp;‘가면의 여왕’의 오지호가 김선아를 지키기 위해 복수 전면전에 돌입한다.&nbsp; 오늘(22일) 오후&nbsp;10시 30분 방송 예정인 채널A 월화드라마 ‘가면의 여왕’(연출 강호중/ 극본 임도완/ 제작 더그레이트쇼, 래몽래인/ 기획 채널A) 9회에서는 재산 포기 조건으로 기도식(조태관 분) 살인사건 정보를 얻어낸 최강후(오지호 분)가 도재이","link":"https://v.daum.net/v/20230522143744223","retrieved":1684736074580},{"title":"키스 마크 가득 옥택연, 원지안 향한 수줍은 표정 (다음 연예 ─ 뉴스 ─ 드라마)","contents":"[OSEN=최나영 기자] ‘가슴이 뛴다’가 저택 지붕 위의 2인 포스터를 첫 공개했다. 오는 6월 26일&nbsp;첫 방송 예정인 KBS 2TV 새 월화드라마 ‘가슴이 뛴다’(연출 이현석, 이민수 / 극본 김하나, 정승주 / 제작 위매드, 몬스터유니온) 측은 22일(오늘) 2인 포스터를 공개, 모두의 가슴을 뛰게 만들 판타지 로맨스 드라마를 예고했다.&nbsp; ‘가슴이","link":"https://v.daum.net/v/20230522143316074","retrieved":1684736074581},{"title":"'닥터 차정숙' 의료사고 휘말린 송지호, '을의 연애' 조아람과 사내연애도 끝? (다음 연예 ─ 뉴스 ─ 드라마)","contents":"[OSEN=최나영 기자] '닥터 차정숙'의 송지호가 의료사고로 인해 멘탈이 무너지는 안타까운 상황을 맞이했다. 송지호는 지난 20일(토)과 21일(일) 방송된 JTBC 토일드라마 ‘닥터 차정숙’에서 여자친구 조아람(전소라 역)과 헤어진 뒤 의료사고에 휘말리기까지 해 보는 이들의 가슴을 철렁하게 했다. 지난 방송에서 전소라와 서정민(송지호 분)은 극 중","link":"https://v.daum.net/v/20230522143115960","retrieved":1684736074581},{"title":"눈빛 돌변한 주연우, 서지혜 끌고 여관行 (다음 연예 ─ 뉴스 ─ 드라마)","contents":"[뉴스엔 이민지 기자] 서지혜, 주연우가 여관에서 포착됐다. 5월 22일 방송되는 KBS 2TV 월화드라마 '어쩌다 마주친, 그대'(극본 백소연/연출 강수연 이웅희) 7회에서 이순애(서지혜 분)가 유범룡(주연우 분)의 손에 이끌려 우정여관 앞에 도착한다. 지난 6회 방송에서 순애는 백윤영(진기주 분)에게 자신의 남자친구인 범룡보다 백희섭(이원정 분)에","link":"https://v.daum.net/v/20230522143043931","retrieved":1684736074587},{"title":"강수지 \"김국진이 생일날 즉석 미역국 끓여줘, 선물은…\" (다음 연예 ─ 뉴스 ─ 예능)","contents":"[마이데일리 = 노한빈 기자] 배우 강수지가 남편이자 방송인 김국진의 사랑꾼 면모를 자랑했다. 21일 유튜브 채널 '강수지tv 살며사랑하며배우며'에는 '수지의 편안한 Talk 11' 영상이 게재됐다. 이날 강수지는 \"오늘은 정말 연락을 많이 받았다\"며 \"제 생일이었다. 그래서 많은 분들에게 메시지를 받았다. 선물도 많이 받았다\"고 말문을 텄다. 이어 강수","link":"https://v.daum.net/v/20230522190013179","retrieved":1684750315510},{"title":"백종원 없어도 괜찮아…'동네멋집', K-카페의 神 손 잡았다 (다음 연예 ─ 뉴스 ─ 예능)","contents":"[OSEN=장우영 기자] SBS 새 예능 ‘손대면 핫플! 동네멋집‘ 쪽박 카페를 대박 카페로 변신시킬 ‘대한민국 최고 카페 전문가’의 정체가 공개됐다. 22일 SBS 새 예능 ‘손대면 핫플! 동네멋집‘(이하 ’동네멋집‘)이 티저 영상을 통해 폐업 직전의 카페를 ‘핫플’로 재탄생시킬 전문가의 정체를 최초로 공개해 관심을 끌고 있다. 그의 정체는 바로 카페","link":"https://v.daum.net/v/20230522184115768","retrieved":1684750315511},{"title":"'37세' 송해나, 맥시멀리스트 고백…신발장에 넘치는 운동화 (다음 연예 ─ 뉴스 ─ 예능)","contents":"(엑스포츠뉴스 김현정 기자) '구해줘 홈즈' 송해나가 맥시멀리스트라고 고백했다. 21일 방송한 MBC '구해줘! 홈즈'에서는 모델 송해나와 그룹 B1A4 출신 배우 차선우가 인턴 코디로 출연했다. 송해나는 \"골 때리고 발품 팔고 갈게요. 복팀의 절친 모델 송해나다\"라고 소개했다. 장동민은 \"복팀장님(박나래)과 많이 친한데 맥시멀리스트 취향이 비슷하다고 하더","link":"https://v.daum.net/v/20230522184002737","retrieved":1684750315514},{"title":"\"사망 시 리더가 지분 갖기로\"…백발소년단, '악마 조항' 계약서 공개 (다음 연예 ─ 뉴스 ─ 예능)","contents":"(엑스포츠뉴스 오승현 기자) 60대 아이돌 백발소년단이 특이한 계약서를 공개했다. 21일 방송한 SBS '미운 우리 새끼'에는 60대 백발의 아이돌 백발소년단 멤버들이 출연했다. 이상민은 백발소년단(BBS)의 등장에 \"죄송한데 검색 한 번 해도 되냐. 믿을 수 없다\"며 이색 남자 아이돌에 대해 의심을 품었다. 백발소년단은 뉴욕대 출신 영화 감독, 대기업 정","link":"https://v.daum.net/v/20230522182003319","retrieved":1684750315516},{"title":"이다해♥세븐 ‘동상이몽2’ 출연 “8년 만나도 안 맞는 부분 있어” (다음 연예 ─ 뉴스 ─ 예능)","contents":"이다해, 세븐 부부가 ‘동상이몽2’에서 결혼식은 물론 신혼 일상을 공개한다. 22일 방송되는 SBS 예능프로그램 ‘동상이몽 시즌2 - 너는 내 운명’(이하 ‘동상이몽’)에서는 세븐, 이다해 부부의 결혼식 비하인드 스토리가 최초로 공개된다. 세븐, 이다해 부부는 결혼식을 앞두고 설레는 마음으로 드레스 피팅에 나섰다. 이다해는 “활동하며 드레스는 많이 입어봤지","link":"https://v.daum.net/v/20230522175714732","retrieved":1684746688742},{"title":"황민호, 은가은이 좋다더니…여자친구 언급에 동공지진 (다음 연예 ─ 뉴스 ─ 예능)","contents":"(엑스포츠뉴스 윤현지 기자) 황민호가 예상치 못한 발언으로 '화밤'을 쥐락펴락 한다. 오는 23일 방송되는 TV조선 '화요일은 밤이 좋아'(이하 '화밤') 69회는 '미스터트롯2 팔인팔색' 특집으로 꾸며진다. 이에 '미스터트롯2'에서 다양한 매력으로 시청자를 즐겁게 했던 김용필, 황민호, 윤준협, 송민준, 추혁진, 장송호, 길병민, 이하준이 출연해 '화밤'","link":"https://v.daum.net/v/20230522175547690","retrieved":1684746688742},{"title":"방은희, ‘절친’ 서태화와 홀딱 벗고 첫만남 “서로 재수없었다” (다음 연예 ─ 뉴스 ─ 예능)","contents":"[뉴스엔 배효주 기자] 방은희와 서태화의 남다른 인연이 공개됐다. 5월 21일 오후 방송된 TV조선 '스타다큐 마이웨이'에서는 방은희가 절친 서태화를 만나 서로의 첫인상을 회상하는 모습이 담겼다. 서태화는 \"97년도 제 데뷔작에서 방은희가 여자 주인공이었다\"는 인연을 밝혔고, 방은희는 \"곽경택 감독님의 '억수탕'이라는 목욕탕 영화였다. 홀딱 벗고 만나","link":"https://v.daum.net/v/20230522174834528","retrieved":1684746688743},{"title":"이장우, 김민재 방문에 “너무 팬입니다” (다음 연예 ─ 뉴스 ─ 예능)","contents":"배우 이장우가 tvN ‘장사천재 백사장’에서 단단한 컨트롤 타워로 거듭났다. 이장우는 지난 21일 방송된 tvN 예능 프로그램 ‘장사천재 백사장’에서 백종원, 소녀시대 유리, 존박과 함께 이탈리아 나폴리를 겨냥한 장사 도전을 이어갔다. 장사가 끝나고 축구선수 김민재 선수가 백반집에 찾아오자 ‘백반져스’는 놀라움과 기쁨을 감추지 못했다. 이전부터 김민","link":"https://v.daum.net/v/20230522174256343","retrieved":1684746688744},{"title":"'이혼' 장가현 \"'우이혼2'서 감정 폭발, 속 시원했다\" 속내 고백 (다음 연예 ─ 뉴스 ─ 예능)","contents":"배우 장가현이 전남편인 그룹 015B 출신 조성민과 출연했던 '우리 이혼했어요 2' 출연 후 심경을 전했다. 22일 방송된 tvN 예능 프로그램 '프리한 닥터'에는 배우 장가현과 그의 딸 예은 씨가 출연했다. 이날 방송에서 장가현은 딸 예은과 함께 프렌치토스트, 토마토 팍시 등 프랑스 가정식을 근사하게 차려 식사를 하는 일상을 공개했다. 식사를 하","link":"https://v.daum.net/v/20230522170921366","retrieved":1684743294514},{"title":"'하트시그널' 아닌 데뷔시그널→범죄시그널→셀럽시그널…비호감 전락한 원조 (다음 연예 ─ 뉴스 ─ 예능)","contents":"[텐아시아=김지원 기자] 《김지원의 까까오톡》 '까놓고, 까칠하게 하는 오늘의 이야기'. 김지원 텐아시아 기자가 연예·방송계 이슈를 까다로운 시선으로 신랄하게 비판합니다. &nbsp; 연애보다 '잿밥'에 더 관심이 많은 것 같다. 채널A '하트시그널' 시리즈의 출연자들 이야기다. 시즌마다 각종 논란으로 시끄러웠던 '하트시그널'이 시즌4도 시작부터 잡음을 겪고 있다","link":"https://v.daum.net/v/20230522170106005","retrieved":1684743294516},{"title":"홍현희, 명품 득템 위해 오픈런→절친들도 질린 집착 (다음 연예 ─ 뉴스 ─ 예능)","contents":"[뉴스엔 이슬기 기자] ‘안다행’ 홍현희와 절친들이 명품(?) 득템 위해 물때 오픈런에 나선다. 5월 22일 방송되는MBC '안싸우면 다행이야'(연출 김명진, 이하 ‘안다행’) 124회에서는 홍현희와 그의 절친들 김용명, 이은지, 가비, 권은빈이 무인도에 출격해 ‘내손내잡’(내 손으로 내가 잡는다)을 펼친다. ‘빽토커’로는 제이쓴과 한승연이 함께한다. 이","link":"https://v.daum.net/v/20230522160708967","retrieved":1684739539421},{"title":"장도연, 손석구 이상형 어필에 화답 “MBTI가 ABCD여도 좋아” (다음 연예 ─ 뉴스 ─ 예능)","contents":"[뉴스엔 이슬기 기자] 장도연이 손석구의 이상형 고백에 응답한다. 5월 23일 방송되는 MBC ‘혓바닥 종합격투기 세치혀’(연출 한승훈, 김진경, 이하 ‘세치혀’)에서는 ‘MZ머니 세치혀’ 김경필이 오직 ‘세치혀’를 위해 만든 ‘소비 MBTI’가 공개된다. 김경필이 ‘수사반장 세치혀’ 김복준을 상대로 ‘10대 90’ 대패를 딛고 설욕전에 나선다. 다시 한","link":"https://v.daum.net/v/20230522160427845","retrieved":1684739539424},{"title":"‘소년판타지’ 180도 다른 모습 예고, 23일 ‘더쇼’ 출격 (다음 연예 ─ 뉴스 ─ 예능)","contents":"[뉴스엔 이민지 기자] MBC ‘소년판타지’ 참가자들이 180도 달라진 무대를 선보인다. ‘소년판타지’ 참가자들은 5월 23일 방송되는 SBS M, SBS FiL ‘더쇼’에 출연해 강승윤과 전소연이 프로듀싱한 세미파이널 신곡 ‘뛰어(RUN)’, ‘SPACEMAN’(스페이스맨) 무대를 꾸민다. MBC ‘쇼! 음악중심’에서 세미파이널 신곡 무대를 최초 공","link":"https://v.daum.net/v/20230522155243368","retrieved":1684739539425},{"title":"장도연 '손석구 이상형'에 하트시그널 \"그분 소비 MBTI가 ABCD여도 좋아\" (다음 연예 ─ 뉴스 ─ 예능)","contents":"[OSEN=최나영 기자]&nbsp;‘돈쭐남’&nbsp;김경필이 더 강력한&nbsp;MZ&nbsp;트렌드인&nbsp;16가지 유형&nbsp;‘소비&nbsp;MBTI’&nbsp;썰로&nbsp;‘세치혀’&nbsp;챔피언 로드에 재도전한다.&nbsp;부자 될 확률&nbsp;1위에 속하는&nbsp;‘소비&nbsp;MBTI’가 공개되는 가운데,&nbsp;김경필이&nbsp;‘썰마스터단’에 잠재적 부자&nbsp;2명이 있다고 밝혀 누구일지 궁금증을 치솟게 한다. 오는&nbsp;23일 오후&nbsp;10시에 방송되는&nbsp;MBC ‘혓바닥 종","link":"https://v.daum.net/v/20230522155215341","retrieved":1684739539453},{"title":"장도연, 손석구 이상형 화답♥ \"그분은 ABCD여도 좋아\" (다음 연예 ─ 뉴스 ─ 예능)","contents":"(엑스포츠뉴스 김현정 기자) '세치혀' 장도연이 배우 손석구의 이상형 언급에 화답한다. 23일 오후 10시에 방송하는 MBC ‘혓바닥 종합격투기 세치혀’에서는 ‘MZ머니 세치혀’ 김경필이 오직 ‘세치혀’를 위해 만든 ‘소비 MBTI’를 공개한다. 김경필이 ‘수사반장 세치혀’ 김복준을 상대로 ‘10대 90’ 대패를 딛고 설욕전에 나선다. 다시 한번 챔피언 자","link":"https://v.daum.net/v/20230522153842886","retrieved":1684739539454},{"title":"밀가루 알러지인데 빵순이? '하트시그널4', 출발부터 거짓 논란ing (다음 연예 ─ 뉴스 ─ 스타)","contents":"[스포티비뉴스=공미나 기자] '하트시그널4'이 방송 전후로 시끌시끌하다. 채널A 예능 프로그램 '하트시그널'은 시그널 하우스에 모인 청춘 남녀들의 연애 리얼리티로, 관찰 연애 예능의 원조격이다. 지난 17일 시즌4가 첫 방송됐다. 이날 가장 주목받은 출연자는 김지영. 승무원 출신에 헤어 모델로 활동 중인 김지영은 순정만화 주인공 같은 비주얼로 등장과","link":"https://v.daum.net/v/20230522191006424","retrieved":1684750320682},{"title":"홍현희 \"준범이, 엄마는 안 닮은 거 같아\"...'미니 제이쓴' 됐네 (다음 연예 ─ 뉴스 ─ 스타)","contents":"[TV리포트=성민주 기자] 코미디언 홍현희가 아들 준범이가 자신을 닮지 않은 것 같다고 밝혔다. 22일 '홍현희 제이쓴의 홍쓴TV'에 공개된 '똥벼리 많이 컸어요!'라는 제목의 영상에서 홍현희는 남편 제이쓴, 아들 준범이와 함께 하는 일상을 공개했다. 벌써 9개월이 된 준범이가 어느새 훌쩍 큰 모습으로 보행기를 자유자재로 이용하는 모습도 영상에 담겼다. 이","link":"https://v.daum.net/v/20230522190730370","retrieved":1684750320683},{"title":"'범죄도시3' 이준혁 \"3대 빌런 떨리고 설레…호쾌하게 맞아 흡족\" (다음 연예 ─ 뉴스 ─ 스타)","contents":"'범죄도시' 3대 빌런이라는 인생캐를 남긴 이준혁이다. 22일 서울 코엑스 메가박스에서 열린 영화 '범죄도시3(이상용 감독)' 언론시사회에서 장첸(윤계상) 강해상(손서구)을 잇는 세 번째 시리즈 빌런 주성철로 분한 이준혁은 \"떨리지만 설레는 마음이다. '범죄도시3'만 생각하고 오랜 시간을 보냈다\"고 운을 뗐다. 이준혁은 \"","link":"https://v.daum.net/v/20230522190703363","retrieved":1684750320684},{"title":"\"인기 무섭기도\" 故 설리 유작 '페르소나2', 韓에서 볼까 (다음 연예 ─ 뉴스 ─ 스타)","contents":"[스포츠투데이 서지현 기자] 故 설리(최진리)의 생전 인터뷰가 담긴 영상이 공개됐다. 이와 함께 그의 유작인 '페르소나: 설리'를 국내에서도 볼 수 있을지 관심이 집중된다. 최근 온라인 커뮤니티와 SNS 등을 통해 설리의 유작 '페르소나: 설리'(이하 '페르소나2')에 참여한 설리의 생전 인터뷰가 공개됐다. 공개된 영상에서 설리는  \"이 사회 안에서 '나의","link":"https://v.daum.net/v/20230522190304272","retrieved":1684750320690},{"title":"'범죄도시3' 마동석 \"자기복제 지양…장기 울리는 액션 소화\" (다음 연예 ─ 뉴스 ─ 스타)","contents":"관객이 열광할 '마동석 장르'가 돌아왔다. 22일 서울 코엑스 메가박스에서 열린 영화 '범죄도시3(이상용 감독)' 언론시사회에서 마동석은 벌써 세 번째 시리즈를 선보이게 된 것에 대해 \"프랜차이즈 범죄 액션을 만들면서 조금씩 디테일하게, 다른 액션을 만들고자 노력하고 있다. 무엇보다 자기 복제를 안 하려고 한다. 재미있다고 계속 하는 건","link":"https://v.daum.net/v/20230522185210986","retrieved":1684750320690},{"title":"'범죄도시3' 이상용 감독 \"1000만 만족도 불안감 커…신선한 시도 노력\" (다음 연예 ─ 뉴스 ─ 스타)","contents":"1000만의 기쁨과 무게를 동시에 견디며 또 최선을 다했다. 22일 서울 코엑스 메가박스에서 열린 영화 '범죄도시3(이상용 감독)' 언론시사회에서 누적관객수 1269만 명의 메가히트작 '범죄도시2' 이후 1년 만에 새 시리즈를 선보이게 된데 대해 이상용 감독은 \"'범죄도시2'가 너무 잘 됐기 때문에 3편 제작을 하는 과정에서 이전만큼","link":"https://v.daum.net/v/20230522185203978","retrieved":1684750320690},{"title":"조현영, 연애 못하는 이유 \"소개팅 성공률 0.01%…별로인 점부터\" (다음 연예 ─ 뉴스 ─ 스타)","contents":"(엑스포츠뉴스 장인영 기자) 그룹 레인보우 출신 조현영이 소개팅 성공률에 대해 밝혔다.&nbsp; 지난 21일 유튜브 채널 그냥 조현영에는 조현영이 더빙에 도전하는 모습이 담겼다.&nbsp; 이날 조현영은 유튜브 만화 '짤툰'의 작가 짤태식을 만나 더빙을 배웠다. \"성대모사 할 수 있냐\"는 짤태식의 물음에 조현영은 \"레인보우가 유독 성대모사를 못하는 걸로 유명했다\"고 자신감","link":"https://v.daum.net/v/20230522185047946","retrieved":1684750320691},{"title":"우도환, '김지연과 애정신' 제작진과 합의했는데...논란 속 삭제 엔딩 (다음 연예 ─ 뉴스 ─ 스타)","contents":"(엑스포츠뉴스 최희재 기자) 배우 우도환이 '조선 변호사' 미방영분을 공개했다가 뭇매를 맞은 가운데, 해당 영상이 합의 하에 공개된 것으로 알려졌다. 22일, 우도환 측 관계자는 엑스포츠뉴스에 \"해당 영상은 감독님 및 제작진 합의 하에 올린 것\"이라고 전했다. 또한 \"우도환 배우가 종영을 맞아 팬들에게 두 캐릭터의 행복한 미래를 보여드리고 싶어서 올렸던 영","link":"https://v.daum.net/v/20230522185003919","retrieved":1684750320691},{"title":"걸그룹♥운동선수는 데스티니…핑클→원더걸스까지 유구한 역사 (다음 연예 ─ 뉴스 ─ 스타)","contents":"[OSEN=장우영 기자] 걸그룹과 운동선수의 사랑은 데스티니(운명)일까. 1세대 걸그룹 핑클부터 원더걸스, 그리고 티아라까지. 걸그룹 멤버들이 운동선수와 사랑에 빠져 화제를 모으고 있다. 걸그룹 원더걸스 출신 유빈이 테니스 선수 권순우와 열애 중이다. 올해로 35살 유빈은 26살 권순우와 열애를 인정, 9살 연상연하 커플이 탄생했다. 유빈 측과 권순우","link":"https://v.daum.net/v/20230522184923910","retrieved":1684750320692},{"title":"재즈 베이시스트 차현 별세…'1세대 대모' 박성연과 활동 (다음 연예 ─ 뉴스 ─ 스타)","contents":"(서울=연합뉴스) 이태수 기자 = 재즈 베이시스트 차현이 22일 별세했다. 항년 72세. 가요계와 유족 등에 따르면 고인은 지난 1970년 미8군 무대에서 음악을 시작했다. 이후 1970년대 초반 '가왕' 조용필과 함께 밴드 활동을 하기도 했다. 차현은 이후 1989년 '한국 재즈계의 대모'로 불리는 1세대 재즈 보컬리스트 박성연이 운영하던 재즈 클럽 '야","link":"https://v.daum.net/v/20230522184223791","retrieved":1684750320693},{"title":"\"감격의 기립박수\" 주지훈X이선균 '탈출', 비주얼+팀플레이로 칸을 사로잡다 (다음 연예 ─ 뉴스 ─ 스타)","contents":"[스포티비뉴스=유은비 기자] 제76회 칸 국제영화제 비경쟁부문 '미드나잇 스크리닝' 공식 초청작 '탈출: PROJECT SILENCE'가 프랑스 칸 현지에서 세계 최초로 상영되며 압도적인 비주얼과 캐릭터들의 최강 팀플레이로 전 세계 관객들의 마음을 정조준했다. 지난 21일(현지시간) 밤 12시 30분 제76회 칸 국제영화제에 초청받은 '탈출: PR","link":"https://v.daum.net/v/20230522184032757","retrieved":1684750320694},{"title":"에스파, 광야 찢고 나왔다…데뷔 3년 만 개인 SNS 개설 (다음 연예 ─ 뉴스 ─ 스타)","contents":"[OSEN=장우영 기자] 그룹 에스파 멤버들이 개인 SNS를 개설, 팬들과 더 활발한 소통을 예고했다. 22일 에스파 카리나, 윈터, 지젤, 닝닝은 각자의 SNS 계정을 생성하고 첫 사진을 올리며 팬들과 소통에 나섰다. 에스파 멤버들은 SNS를 개설한 지 약 5시간 만에 100만 팔로워를 가뿐하게 돌파하며 뜨거운 인기를 자랑했다. 오후 6시 30분 현재","link":"https://v.daum.net/v/20230522183736685","retrieved":1684750320695},{"title":"백종원 “약과가 비싼 이유? 직접 만들어보면 알게 돼” (다음 연예 ─ 뉴스 ─ 스타)","contents":"[TV리포트=이혜미 기자] 사업가 겸 방송인 백종원이 약과 레시피 개발에 나섰다. 22일 백종원이 운영하는 유튜브 채널엔 “약과 라이팅의 시작”이라는 제목의 영상이 업로드 됐다. 공개된 영상엔 예산시장 내 위치한 떡집을 위해 약과 레시피 개발에 도전한 백종원의 모습이 담겼다. 한 달 여의 연구에도 원하는 맛을 찾는데 어려움을 겪은 그는 “우리가 원하는 건","link":"https://v.daum.net/v/20230522182901512","retrieved":1684750320697},{"title":"'범죄도시3' 마동석 \"8편까지 기획… 관객들이 원한다면 계속할 것\" (다음 연예 ─ 뉴스 ─ 스타)","contents":"대한민국을 대표하는 범죄 액션 영화 '범죄도시3'가 돌아온다. 22일 서울시 강남구 삼성동 메가박스 코엑스에서는 '범죄도시3'의 언론시사회와 기자간담회가 열렸다. 이날 시사회 직후 열린 기자간담회에서는 연출을 맡은 이상용 감독을 비롯해 배우 마동석, 이준혁, 아오키 무네타카 씨 등이 참석했다. '범죄도시3'는 괴물형사 '마석도'(마동석)가 서울 광수대로","link":"https://v.daum.net/v/20230522182707481","retrieved":1684750320698},{"title":"엔하이픈, '욕심'에서 비롯되는 피의 '연결' (다음 연예 ─ 뉴스 ─ 스타)","contents":"기사내용 요약 오늘 미니 4집 '다크 블러드' 발매 [서울=뉴시스]문예빈 인턴 기자 = \"저희 팀의 키워드라고 하면 욕심이라는 단어가 생각나요.\" 그룹 엔하이픈(ENHYPEN)이 한층 성장한 모습을 예고하며 새로운 서사의 포문을 열었다. 22일 오후 엔하이픈은 서울 안암동 고려대학교 화정체육관에서 개최된 미니 4집 '다크 블러드(DARK BLOOD)'","link":"https://v.daum.net/v/20230522182535444","retrieved":1684750320702},{"title":"엠마 스톤, MCU 합류 출연료 탓 불발? “263억원 요구” (다음 연예 ─ 뉴스 ─ 해외)","contents":"[뉴스엔 배효주 기자] 엠마 스톤이 마블 스튜디오의 새 영화 '판타스틱 포'에 합류할 뻔 했으나, 결국 성사되지 못했다는 주장이 나왔다. 마블 스튜디오가 MCU를 이끌 새로운 영화 '판타스틱 포'의 캐스팅 라인업을 꾸리고 있는 가운데, 엠마 스톤이 캐릭터의 중심이 되는 인물인 수 스톰(인비저블 우먼) 역을 제안 받았지만, 끝내 협상이 결렬됐다는 소식이","link":"https://v.daum.net/v/20230522184635870","retrieved":1684750325853},{"title":"노윤서, 칸에 깜짝 등장한 라이징 스타‥블랙드레스로 뽐낸 성숙미 (다음 연예 ─ 뉴스 ─ 해외)","contents":"[뉴스엔 배효주 기자] 노윤서가 칸 국제영화제가 한창인 프랑스 칸에 깜짝 등장해 호기심을 모았다. 노윤서는 5월 21일(현지시간) 프랑스 칸에서 열린 '케어링 우먼 인 모션 어워즈'(Kering Women In Motion Awards)에 참석했다. 노윤서 측에 따르면 해당 시상식은 다국적 럭셔리 패션 그룹인 케어링 측이 주최한 행사다. 포토월에 오른","link":"https://v.daum.net/v/20230522180712051","retrieved":1684746698967},{"title":"전 연인 폭행 혐의로 체포됐던 마블 배우, 새 여친 생겼다 (다음 연예 ─ 뉴스 ─ 해외)","contents":"[티브이데일리 김종은 기자] 폭행 논란으로 구설수에 오른 조나단 메이저스가 이번엔 열애설에 휘말렸다. 미국 연예매체 TMZ는 22일(현지시간) \"조나단 메이저스가 8살 연상 배우 메건 굿과 열애 중이다\"라고 보도했다. 이와 함께 매체가 공개한 영상과 사진에 따르면 조나단 메이저스와 메건 굿은 뉴욕을 떠나 LA의 한 공항에 도착한 모습. 이 가운데 두 사","link":"https://v.daum.net/v/20230522174726489","retrieved":1684746698970},{"title":"“부부싸움 끝냈나” 벤 애플렉♥제니퍼 로페즈, 쇼핑하며 달달한 키스 (다음 연예 ─ 뉴스 ─ 해외)","contents":"[마이데일리 = 곽명동 기자]최근 불화설에 휩싸였던 벤 애플렉(50), 제니퍼 로페즈(53) 부부가 공개 키스로 주목을 끌었다. 페이지식스는 21일(현지시간) “이들은 지난 20일 비버리힐스에서 쇼핑을 하며 사랑스러운 모습을 보여주었다”면서 “캘리포니아의 햇살 아래서 입술을 맞대고 손을 잡았다”고 전했다. 로페즈는 전남편 마크 앤서니와 함께 살고 있는","link":"https://v.daum.net/v/20230522174225328","retrieved":1684746698974},{"title":"‘앤트맨3’ 빌런 배우, 전여친 폭행 혐의 2달만 새 여친 생겼다‥8세 연상 (다음 연예 ─ 뉴스 ─ 해외)","contents":"[뉴스엔 배효주 기자] '앤트맨3'에서 빌런을 연기한 조나단 메이저스가 여성을 폭행해 논란을 일으킨 지 두 달 만에 열애설이 제기됐다. 5월 22일(현지시간) 해외 매체 TMZ 등 다수의 외신에 따르면 조나단 메이저스(33)는 8세 연상의 배우 메건 굿(41)과 열애 중이다. 두 사람이 뉴욕에서 LA로 함께 떠나는 모습이 파파라치 카메라에 포착된 것.","link":"https://v.daum.net/v/20230522172124716","retrieved":1684746698976},{"title":"엠마 스톤, 마블 영화 거절...\"출연료 263억 원해\" (다음 연예 ─ 뉴스 ─ 해외)","contents":"[TV리포트=이수연 기자] 할리우드 배우 엠마 스톤이 마블 영화 출연을 거절했다. 20(현지 시간) 미국 영화매체 커밍순은 \"엠마 스톤은 마블과 출연료 협상 후 캐스팅 제안을 거절했다\"고 보도했다. 마블 스튜디오가 영화 '판타스틱 포' 출연진을 물색하고 있는 가운데 엠마 스톤이 수 스톰(인비저블 우먼) 역에 제안을 받았으나, 결국 협상이 결렬된 것으로 전","link":"https://v.daum.net/v/20230522171530533","retrieved":1684746698977},{"title":"King & Prince 두 명 남는다 “세 멤버 탈퇴→소속사 쟈니스 퇴소” (다음 연예 ─ 뉴스 ─ 해외)","contents":"[뉴스엔 박수인 기자] 일본 그룹 King &amp; Prince(킹앤프린스) 히라노 쇼, 진구지 유타, 키시 유타가 팀을 탈퇴한다. 히라노 쇼, 진구지 유타는 5월 22일 쟈니스 사무소를 퇴소하고 키시 유타는 올해 가을에 퇴소할 예정이다. 이로써 King &amp; Prince는 나가세 렌과 타카하시 카이토 두 명이 된다. 키시 유타는 쟈니스 사무소 내 블로그를 통해","link":"https://v.daum.net/v/20230522165933919","retrieved":1684743306541},{"title":"숀 펜, 우크라 전쟁 다룬 영화 출연…올 여름 촬영 예정 (다음 연예 ─ 뉴스 ─ 해외)","contents":"(엑스포츠뉴스 이창규 기자) 할리우드 배우 숀 펜이 우크라이나의 전쟁을 다룬 영화에 출연하는 것이 확정됐다. 21일(현지시간) 미국 할리우드 리포터(THR)는 숀 펜이 우크라이나의&nbsp;전쟁에 대한 이야기를 담은 '동물의 눈으로 본 전쟁'(War Through the Eyes of Animals).에 출연하기로 결정했다고 보도했다. 이 작품은 우크라이나의 감독","link":"https://v.daum.net/v/20230522163822170","retrieved":1684743306544},{"title":"'D-2' 인어공주 \"흑인 주인공이 삶을 변화시킬 것\" (다음 연예 ─ 뉴스 ─ 해외)","contents":"[TV리포트=이예은 기자] 흑인 인어공주가 흑인 소녀들의 삶에 희망을 불어넣을 것을 예고했다. 외신 매체 더 가디언즈는 20일(현지 시간) 영화 '인어공주'에서 주인공 에리얼로 출연한 배우 할리 베일리(23)와의 인터뷰를 공개했다.&nbsp; '인어공주'는 제작 단계에서부터 원작과 다른 캐스팅으로 파장이 일었다.&nbsp;특히 주인공 에리엘과 다른 할리 베일리의 인종과 외","link":"https://v.daum.net/v/20230522154530114","retrieved":1684739550746},{"title":"'결별설' 메간 폭스ㆍ머신 건 켈리 커플, 두 달 만에 재결합 (다음 연예 ─ 뉴스 ─ 해외)","contents":"[티브이데일리 김종은 기자] 최근 결별설이 불거졌던 미국 배우 메간 폭스와 래퍼 머신 건 켈리가 다정한 모습으로 공식석상에 나타났다. 메간 폭스와 머신 건 켈리는 최근 뉴욕시티에서 열린 2023 스포츠 일러스트레이티드 스윔슈트 이슈 레드카펫 행사에 동반 참석했다. 이날 메간 폭스는 가슴 부분이 파인 파격적인 시스루 드레스를 입고 등장해 시선을 사로잡았으","link":"https://v.daum.net/v/20230522150744659","retrieved":1684736092089},{"title":"양자경 \"중국·아시아계 배역 제안 안 받아 좋다…'에에올' 속편 NO\" (다음 연예 ─ 뉴스 ─ 해외)","contents":"(엑스포츠뉴스 이창규 기자) 배우 양자경이 자신에게 아카데미상을 안겨준 '에브리씽 에브리웨어 올 앳 원스'(에에올)의 속편 대해 언급했다. 지난 20일(현지시간) 제76회 칸 영화제의 케링 우먼 인 모션 행사에 참석한 양자경은 과거 '와호장룡'으로 칸 영화제를 처음 찾았을 당시를 회상했다. 그는 \"당시 '와호장룡'이 월드와이드 2억 달러 이상의 수익을 올리","link":"https://v.daum.net/v/20230522145242936","retrieved":1684736092099},{"title":"메간 폭스♥머신 건 켈리, 2개월만 재결합…결혼계획 중단 (다음 연예 ─ 뉴스 ─ 해외)","contents":"[뉴스엔 황혜진 기자] 미국 배우 메간 폭스(Megan Fox)와 미국 가수 겸 배우 머신 건 켈리(Machine Gun Kelly)가 재결합 후 신뢰를 회복 중이다. 미국 매체 피플(Peole)은 5월 19일(현지시간) \"메간 폭스와 머신 건 켈리가 천천히 화해 중이다. 하지만 결혼 계획은 중단됐다\"고 전했다. 해당 보도에 따르면 머신 건 켈리는 메간","link":"https://v.daum.net/v/20230522135304438","retrieved":1684732283161},{"title":"양자경, '에에올' 속편은 없다...\"아시아인 역 그만할 것\" (다음 연예 ─ 뉴스 ─ 해외)","contents":"[TV리포트=이수연 기자] 아카데미를 휩쓴 영화 '에브리씽 에브리웨어 올 앳 원스'의 후속작은 없다. 최근 양자경(Michelle Yeoh)은 제76회 칸 국제영화제 동안 열린 '케링 우먼 인 모션'(Kering Women in Motion) 시상식에 참석했다. 이날 그는 20여 년 전 영화 '와호장룡 - 운명의 검'을 통해 칸 국제영화제에 처음 왔을 때","link":"https://v.daum.net/v/20230522131030257","retrieved":1684728804162},{"title":"디카프리오♥지지 하디드, 칸영화제 나란히 참석 “데이트할까” (다음 연예 ─ 뉴스 ─ 해외)","contents":"[마이데일리 = 곽명동 기자]할리우드 스타 레오나르도 디카프리오(48)와 열애중인 미국 모델 지지 하디드(28)가 칸 국제영화제 레드카펫을 밟았다. 이들이 영화제 기간중 데이트를 즐길지 주목된다. 지지 하디드는 21일(현지시간) 프랑스 칸 팔레 데 페스티벌에서 열린 영화 ‘파이어브랜드’ 레드카펫 행사에 참석했다. 데일리메일은 “지지 하디드는 걸을 때마","link":"https://v.daum.net/v/20230522110248010","retrieved":1684721394395},{"title":"제니퍼 로런스, 탈레반 치하 여성 삶 담은 다큐 제작 (다음 연예 ─ 뉴스 ─ 해외)","contents":"(서울=연합뉴스) 유한주 기자 = \"당신들은 학교와 대학들을 폐쇄했다. 차라리 날 죽여라.\" 할리우드 배우 제니퍼 로런스가 아프가니스탄 치하에서 탄압받는 여성들의 삶을 다룬 다큐멘터리를 제작했다고 영국 일간 가디언·BBC 방송이 21일(현지시간) 보도했다. 이날 제76회 칸국제영화제에서는 로런스와 그의 친구 저스틴 차로키가 공동 제작한 다큐멘터리 '빵과 장","link":"https://v.daum.net/v/20230522105057408","retrieved":1684721394397}]}