{"title":"Combined feed","url":"https://MOVIECORD.github.io/entertain.daum/all.xml","elements":[{"title":"'안녕, 할부지' 감독 \"푸바오 보내며 왜 우냐고요?\" (다음 연예 ─ 뉴스 ─ 영화)","contents":"[스타뉴스 | 김나연 기자] 심형준 감독 / 사진=에버랜드\"푸바오를 보내며 운 사람들의 심정을 이 영화를 통해 공감하실 겁니다.\" 우연한 기회에 연출하게 된 다큐멘터리. 심형준 감독은 끝을 모르고 몰입하고, 빠져들었다. '안녕, 할부지'의 감독이 푸바오를 떠나보내며 함께 울었다. 지난 29일 서울시 종로구 삼청로의 한 카페에서 영화 '안녕, 할부지'(","link":"https://v.daum.net/v/20240901070153618","retrieved":1725142385139},{"title":"\"양성평등 가치 실현\"…벡델데이가 주목하는 올해의 작품은? (다음 연예 ─ 뉴스 ─ 영화)","contents":"매년 양성평등주간(9월 첫째 주)에 맞춰 열리는 행사 여성 서사·여성 캐릭터들이 두드러진 작품 조명 [더팩트｜박지윤 기자] 다양성을 추구하는 여성 영화를 조명하고 영화계에 성평등을 지향하고자 하는 취지에서 등장한 벡델데이가 어느덧 다섯 번째 행사를 맞이한다. 2020년부터 양성평등주간(매년 9월 첫째 주)에 맞춰 열리고 있는 벡델데이가 올해에는 어떤","link":"https://v.daum.net/v/20240901000038790","retrieved":1725117182207},{"title":"“5분간 기립 박수” 정호연, 케이트 블란쳇과 어깨 나란히 (다음 연예 ─ 뉴스 ─ 영화)","contents":"배우 정호연이 ‘베니스국제영화제’에서 5분 동안 기립 박수를 받았다. 정호연이 지난 29일, 30일(현지 시각) 이틀에 걸쳐 '제81회 베니스국제영화제' 레드카펫 위에 올랐다. 양일 동안 진행된 Apple TV+ ‘누군가는 알고 있다 — Disclaimer’의 프리미어 시사회에 참석한 정호연은 첫날 강렬한 레드 드레스로 시선을 압도했다. 이튿날 그는 과","link":"https://v.daum.net/v/20240831194251560","retrieved":1725102605536},{"title":"남진, 나훈아와 라이벌 구도에 얽힌 비밀 (다음 연예 ─ 뉴스 ─ 영화)","contents":"가수 남진과 나훈아는 '세기의 라이벌'로 불리곤 했다. 남진은 나훈아와의 라이벌 구도가 '연예계의 비지니스' 때문에 형성됐다고 털어놨다. 두 사람 사이에는 재밌는 인연 또한 존재한다. 나훈아는 남진 친구의 제자다. 남진은 지난 29일 서울 종로구 삼청동 한 카페에서 영화 '오빠, 남진' 관련 인터뷰를 진행했다. '오빠, 남진'은 대한민국 최초의 팬덤을 이끈","link":"https://v.daum.net/v/20240831153831848","retrieved":1725088266292},{"title":"정호연 ‘베니스의 여인’···케이트 블란쳇과 투샷 환호 (다음 연예 ─ 뉴스 ─ 영화)","contents":"배우 정호연이 ‘제81회 베니스국제영화제(81st Venice International Film Festival)’에서 기립 박수를 받았다. 정호연이 지난 29일, 30일(현지 시각) 이틀에 걸쳐 ‘제81회 베니스국제영화제’ 레드카펫 위에 올랐다. 양일 동안 진행된 Apple TV+ ‘누군가는 알고 있다 — Disclaimer’의 프리미어 시사회에 참","link":"https://v.daum.net/v/20240831150421520","retrieved":1725084970353},{"title":"정호연, 이틀 연속 '베니스영화제' 레드카펫 접수 (다음 연예 ─ 뉴스 ─ 영화)","contents":"[스포츠투데이 백지연 기자] 배우 정호연이 '제81회 베니스국제영화제(81st Venice International Film Festival)'에서 기립 박수를 받았다. 정호연이 지난 29일, 30일(현지 시각) 이틀에 걸쳐 '제81회 베니스국제영화제' 레드카펫 위에 올랐다. 양일 동안 진행된 Apple TV+ ‘누군가는 알고 있다 — Disclaimer’","link":"https://v.daum.net/v/20240831150031475","retrieved":1725084970354},{"title":"영화 '오징어게임: 아메리카' 나온다 (다음 연예 ─ 뉴스 ─ 영화)","contents":"[TV리포트=전하나 기자] 넷플릭스 오리지널 시리즈 '오징어 게임'의 미국 리메이크 버전인 '오징어게임: 아메리카' 제작에 관한 소식이 들려왔다. 지난 29일(현지 시간), 외신매체 '월드 오브 릴'(World of Reel)가 넷플릭스가 '오징어 게임'을 미국식으로 재해석한 '오징어게임: 아메리카'를 제작할 예정이라고 보도했다. 특히 '벤자민 버튼의 시간","link":"https://v.daum.net/v/20240831144528362","retrieved":1725084970357},{"title":"“5분 동안 기립 박수” 정호연, ‘베니스국제영화제’서 눈부신 존재감 (다음 연예 ─ 뉴스 ─ 영화)","contents":"배우 정호연이 ‘제81회 베니스국제영화제(81st Venice International Film Festival)’에서 기립 박수를 받았다. 정호연이 지난 29일, 30일(현지 시각) 이틀에 걸쳐 ‘제81회 베니스국제영화제’ 레드카펫 위에 올랐다. 양일 동안 진행된 Apple TV+ ‘누군가는 알고 있다 — Disclaimer’의 프리미어 시사회에 참석한","link":"https://v.daum.net/v/20240831141200065","retrieved":1725081176603},{"title":"정호연, 제81회 베니스국제영화제서 5분동안 기립박수 받아 (다음 연예 ─ 뉴스 ─ 영화)","contents":"[텐아시아=류예지 기자]배우 정호연이 '제81회 베니스국제영화제(81st Venice International Film Festival)'에서 기립 박수를 받았다. 정호연이 지난 29일, 30일(현지 시각) 이틀에 걸쳐 '제81회 베니스국제영화제' 레드카펫 위에 올랐다. 양일 동안 진행된 Apple TV+ ‘누군가는 알고 있다 — Disclaimer’의","link":"https://v.daum.net/v/20240831133702712","retrieved":1725081176603},{"title":"임영웅→하츄핑·푸바오…영화계 들썩이는 거대 팬덤의 '힘' (다음 연예 ─ 뉴스 ─ 영화)","contents":"[마이데일리 = 김지우 기자] 대형 팬덤을 겨냥한 영화들이 '억' 소리 나는 저력을 발휘하고 있다. 이달 초 개봉한 애니메이션 영화 '사랑의 하츄핑'은 운명의 소울메이트를 찾아 나선 로미와 하츄핑의 첫 만남을 그린다. 개봉 9일 만에 손익분기점인 50만을 넘었으며, 개봉 20일 만에 누적관객수 80만, 누적 매출액 72억 4480만 원을 달성했다. 77","link":"https://v.daum.net/v/20240831130351447","retrieved":1725077762247},{"title":"정호연, 베니스영화제서 5분간 기립박수·환호…\"Z세대 관객 핵심 인물\" 극찬 (다음 연예 ─ 뉴스 ─ 영화)","contents":"(사진=베니스국제영화제 공식 SNS)[이데일리 스타in 김보영 기자] 배우 정호연이 ‘제81회 베니스국제영화제’에서 약 5분간 기립 박수를 받았다. 정호연이 지난 29일, 30일(현지 시각) 이틀에 걸쳐 ‘제81회 베니스국제영화제’ 레드카펫 위에 올라 아우라를 발산했다. 양일간 진행된 애플 TV+ 시리즈 ‘누군가는 알고 있다 -Disclaimer’의 프리","link":"https://v.daum.net/v/20240831124450259","retrieved":1725077762247},{"title":"‘에이리언: 로물루스’ 15일째 1위, 장르물 어필 (다음 연예 ─ 뉴스 ─ 영화)","contents":"[티브이데일리 이기은 기자] 영화 '에이리언: 로물루스'(감독 페데 알바레즈)가 박스오피스 1위로 질주 중이다. 31일 영화진흥위원회 영화관입장권 통합전산망 집계에 따르면 '에이리언: 로물루스'는 지난 30일 하루 전국 1007개 스크린에서 4만 6596명의 관객을 불러 모으며 박스오피스 1위를 굳건히 유지했다. 누적 관객 수는 146만 95명으로 집계됐다","link":"https://v.daum.net/v/20240831115352899","retrieved":1725074017849},{"title":"정호연, 베니스 영화제서 5분 기립박수 세례…케이트 블란쳇과 ‘투샷’ 화제 (다음 연예 ─ 뉴스 ─ 영화)","contents":"배우 정호연이 제81회 베니스국제영화제에서 기립 박수를 받았다. 정호연이 지난 29일, 30일(현지 시각) 이틀에 걸쳐 제81회 베니스국제영화제 레드카펫에 올랐다. 양일 동안 진행된 애플TV+ ‘누군가는 알고 있다 — 디스클레이머(Disclaimer)’(이하 ‘누군가는 알고 있다’)의 프리미어 시사회에 참석한 정호연은 첫날 강렬한 레드 드레스로 시선을","link":"https://v.daum.net/v/20240831112433689","retrieved":1725074017851},{"title":"'서이초 사건' 이전... 먼저 세상을 떠난 선생님이 있었다 (다음 연예 ─ 뉴스 ─ 영화)","contents":"제 21회 EBS 국제다큐영화제가 8월 19일부터 25일까지 열렸습니다. 32개국 53편에 달하는 다큐멘터리 작품 중 눈에 띄는 다큐를 소개합니다. &lt;편집자말&gt; [조영준 기자] ▲ &nbsp;제21회 EBS 국제다큐영화제 상영작 &lt;선생&gt; 스틸컷ⓒ EBS국제다큐영화제(*이 글은 영화의 스포일러를 포함하고 있습니다.) 01. 2023년 여름, 대한민국 각지에서 교사들이","link":"https://v.daum.net/v/20240831105404340","retrieved":1725070150315},{"title":"참으로 어디에나 있다, ‘나의 자리’에서 숨 쉬는 여성들 (다음 연예 ─ 뉴스 ─ 영화)","contents":"1999년 거제도의 한 오락실 앞. 펌프 위에서 두명의 남고생이 기량을 뽐내고 있다. 화려한 퍼포먼스가 끝나자 구경하고 있던 아이들이 박수를 친다. “거제 촌놈들, 뭐 귀신이라도 봤나. 부산서 이 정도는…(일도 아이지).” 거들먹거리며 스코어를 확인한 도시 청년들은 그러나 당황한다. 순위가 그다지 높지 않기 때문이다. 어리둥절해하는 그들 앞에 최고 기록의","link":"https://v.daum.net/v/20240831100731855","retrieved":1725070150315},{"title":"\"아빠 보고싶어\"...장나라, 딸 오열에 '흔들'→해고 위기까지 (다음 연예 ─ 뉴스 ─ 드라마)","contents":"(엑스포츠뉴스 오수정 기자) '굿파트너'에서 장나라가 흔들렸다.&nbsp; 지난 31일 방송된 SBS 금토드라마 '굿파트너' 11회에서는 김지상(지승현 분)과 이혼 후 차은경(장나라)의 모습이 그려졌다.&nbsp; 앞선 방송에서 차은경은 김지상(지승현)이 양육권을 포기하면서 소송을 끝내고 협의 이혼으로 마무리됐다.&nbsp; 차은경의 대리인이었던 한유리(남지현)는 이혼 후 출근한 차","link":"https://v.daum.net/v/20240901070155619","retrieved":1725142390285},{"title":"'굿파트너' 유나, 父 지승현 그리움에 오열→장나라, 남지현에 AS요청 (다음 연예 ─ 뉴스 ─ 드라마)","contents":"[스타뉴스 | 정은채 기자] /사진='굿파트너' 방송화면 캡쳐'굿파트너'에서 장나라가 '불륜 남편' 지승현과 이혼 후에도 험난한 길을 걸으며 안타까움을 자아냈다. 8월 31일 밤 방송된 SBS 금토드라마 '굿파트너' 11회에서는 차은경(장나라 분)이 한유리(남지현 분)에게 이혼 소송 'AS'를 요청하는 장면이 그려졌다. 이날 한유리는 김지상(지승현 분)","link":"https://v.daum.net/v/20240901070148609","retrieved":1725142390286},{"title":"'굿파트너' 장나라, 유나와 더불어 오열 연기 美쳤어···이혼 후 위기 봉착 (다음 연예 ─ 뉴스 ─ 드라마)","contents":"[OSEN=오세진 기자] ‘굿파트너’ 장나라가 딸 유나를 안고 오열했다. 31일 방영한 SBS&nbsp;금토드라마&nbsp;‘굿파트너’(극본 최유나,&nbsp;연출 김가람,&nbsp;기획·제작 스튜디오S·스튜디오앤뉴)에서는 딸 재희(유나 분)와 오붓한 시간을 보내는 차은경(장나라 분)의 모습이 그려졌다. 차은경은&nbsp;난데없는 휴가를 받게 됐다. 오대규(정재성 분)는 차은경에게&nbsp;“대형 로펌에서","link":"https://v.daum.net/v/20240901065954532","retrieved":1725142390288},{"title":"정해인 상의탈의, 정소민 침대에 눕혔다 “얘네 이상해” (다음 연예 ─ 뉴스 ─ 드라마)","contents":"정해인과 정소민이 묘한 오해를 샀다. 8월 31일 방송된 tvN 토일드라마 ‘엄마친구아들’ 5회(극본 신하은/연출 유제원)에서 최승효(정해인 분)는 배석류(정소민 분)과 몸싸움을 했다. 배석류는 아침에 동생 배동진(이승협 분)이 깨어나지 않자 때려서 깨웠다. 하지만 이불 안에 잠들어 있던 사람은 최승효. 최승효는 그만 때리라며 배석류의 손을 잡고 제지","link":"https://v.daum.net/v/20240901060708222","retrieved":1725138677800},{"title":"정해인, 전여친 서지혜 덕 정소민 사랑자각 “좋아할 수밖에 없어” (다음 연예 ─ 뉴스 ─ 드라마)","contents":"서지혜 덕분에 정소민이 꿈을 찾고 정해인은 사랑을 자각했다. 8월 31일 방송된 tvN 토일드라마 ‘엄마친구아들’ 5회(극본 신하은/연출 유제원)에서는 최승효(정해인 분)와 배석류(정소민 분)가 장태희(서지혜 분) 덕분에 새로운 국면을 맞았다. 과거 최승효는 배석류 미국 유학시절 찾아가 고백하려 했지만 배석류에게는 이미 새 남자친구가 생긴 후였다. 현","link":"https://v.daum.net/v/20240901060656217","retrieved":1725138677801},{"title":"서지혜, 정소민 앞 정해인과 키스 ‘전여친 특별출연’ (다음 연예 ─ 뉴스 ─ 드라마)","contents":"서지혜가 정해인 전여친 장태희로 특별출연했다. 8월 31일 방송된 tvN 토일드라마 ‘엄마친구아들’ 5회(극본 신하은/연출 유제원)에서는 최승효(정해인 분)의 전여친 장태희(서지혜 분)가 찾아왔다. 최승효와 배석류(정소민 분)가 말다툼을 하는 사이 장태희가 최승효를 백허그하며 “자기야 오랜만이야”라고 인사해 모두를 얼어붙게 만들었다. 윤명우(전석호 분","link":"https://v.daum.net/v/20240901060652215","retrieved":1725138677802},{"title":"정해인, 정소민에 “손예진은 건드리지 마” 폭소 (다음 연예 ─ 뉴스 ─ 드라마)","contents":"정해인이 드라마 ‘밥 잘 사주는 예쁜 누나’ 상대역 배우 손예진을 언급했다. 8월 31일 방송된 tvN 토일드라마 ‘엄마친구아들’ 5회(극본 신하은/연출 유제원)에서 최승효(정해인 분)는 배석류(정소민 분)의 요리 실력을 불신했다. 최승효는 남산에 다녀와 요리를 해준다는 배석류에게 “남산에 갔으면 남산 돈가스가 국룰 아니냐. 뭐한다고 이렇게 장을 보냐","link":"https://v.daum.net/v/20240901060557202","retrieved":1725138677803},{"title":"'굿파트너' 장나라. 남지현에 \"아무도 날 필요로 하지 않는 것 같은데 어쩌지?\" 눈물 (다음 연예 ─ 뉴스 ─ 드라마)","contents":"[SBS연예뉴스 | 김효정 에디터] 장나라가 한유리에게 AS를 의뢰했다. 31일 방송된 SBS 금토 드라마 '굿파트너'에서는 재희와 함께 휴가를 떠난 차은경의 모습이 그려졌다. 이날 차은경은 재희와 함께 휴가를 떠났다. 그리고 그곳에서 아빠의 부재를 느끼는 재희를 보며 안타까운 마음을 감추지 못했다. 또한 어느 누구도 자신을 찾지 않는 휴대전화를 보며 씁쓸","link":"https://v.daum.net/v/20240901003900986","retrieved":1725120916656},{"title":"'엄친아' 5회, 황당 '배장금' 서사 '빈축'..\"정해인·정소민 무슨 죄\" (다음 연예 ─ 뉴스 ─ 드라마)","contents":"[스타뉴스 | 김나라 기자] /사진=tvN '엄마친구아들' 캡처'엄마친구아들' 5회'엄마친구아들'이 5회에서 빈약한 서사의 한계를 드러내며 시청자들의 아쉬움을 자아냈다. 8월 31일 오후 방송된 tvN 토일드라마 '엄마친구아들'(연출 유제원｜극본 신하은) 5회는 '고백'이라는 부제 아래 최승효(정해인 분)와 배석류(정소민 분)가 언제나처럼 티격태격하는 모","link":"https://v.daum.net/v/20240901002658958","retrieved":1725120916658},{"title":"지진희, 손나은 울린 눈물의 사과 \"내가 어떻게 널 후회하니\" (다음 연예 ─ 뉴스 ─ 드라마)","contents":"[TV리포트=남금주 기자] 지진희가 손나은에게 진심으로 사과한 가운데, 김지수가 두 사람의 내기를 알게 됐다. 31일 방송된 tvN 토일드라마 '가족X멜로' 7회에서는 남태평(최민호 분)이 변미래(손나은)게 마음을 슬쩍 전달했다. 이날 오재걸(김영재)은 아내에게 양육비를 송금해 달란 독촉 연락을 받았다. 오재걸은 변무진(지진희)의 이름으로 대출을 받으려","link":"https://v.daum.net/v/20240901001032857","retrieved":1725117186476},{"title":"'가족X멜로' 김지수, 지진희vs손나은 재결합 내기한 사실 알고 '분노' (다음 연예 ─ 뉴스 ─ 드라마)","contents":"(엑스포츠뉴스 이이진 기자) '가족X멜로' 김지수가 지진희와 손나은 사이에 거래가 있었다는 것을 알고 분노했다. 31일 방송된 JTBC 금토드라마 '가족X멜로' 7회에서는 금애연(김지수 분)이 변무진(지진희)과 변미래(손나은)가 내기를 벌였다는 사실을 알게 된 모습이 그려졌다. 이날 변미래는 변무진과 금애연을 모텔에서 마주쳤고, 짐을 챙겨 집을 나갔다. 변","link":"https://v.daum.net/v/20240901000951854","retrieved":1725117186481},{"title":"'굿파트너' 장나라, \"퇴사를 말씀하시는 거냐?\"…정재성의 '퇴사 권유'에 당황 (다음 연예 ─ 뉴스 ─ 드라마)","contents":"[SBS연예뉴스 | 김효정 에디터] 정재성이 장나라에게 퇴사를 권했다. 31일 방송된 SBS 금토 드라마 '굿파트너'에서는 로펌의 대표에게 퇴사 권유를 받은 차은경의 모습이 그려졌다. 이날 대정의 대표 오대규는 차은경을 자신의 방으로 불렀다. 그리고 그는 \"차변호사 개인적인 일로 그동안 시끄러웠는데 이제 다 끝났지 않냐. 이후 차변 계획을 들어보려고 불렀다","link":"https://v.daum.net/v/20240831235701761","retrieved":1725117186482},{"title":"'가족X멜로' 최민호, ♥손나은에 출생의 비밀 고백…\"호적상 아버지가 사실은 형\" (다음 연예 ─ 뉴스 ─ 드라마)","contents":"(엑스포츠뉴스 이이진 기자) '가족X멜로' 최민호가 손나은에게 출생의 비밀을 밝혔다. 31일 방송된 JTBC 금토드라마 '가족X멜로' 7회에서는 남태평(최민호 분)이 변미래(손나은)에게 가정사를 고백한 모습이 그려졌다. 이날 변미래는 \"내가 제일 좋아하는 사람이 내가 제일 싫어하는 사람이랑 다시 만나는 게 싫어요. 엄마가 얼마나 힘들었는지 쭉 보면서 자랐으","link":"https://v.daum.net/v/20240831233648683","retrieved":1725117186482},{"title":"\"몰라서 묻냐\"…최민호, 손나은에 복잡한 가정사·마음 고백 (다음 연예 ─ 뉴스 ─ 드라마)","contents":"[TV리포트=남금주 기자] 손나은과 최민호가 서로를 위로했다. 31일 방송된 tvN 토일드라마 '가족X멜로' 7회에서는 남태평(최민호 분)의 집에 간 변미래(손나은)의 모습이 그려졌다. 이날 모텔에서 변무진(지진희), 금애연(김지수)을 목격한 변미래는 집을 나왔다. 변미래는 금애연에게 '둘 다는 못 가져. 엄마가 아버지랑 잘 되면 영원히 집 나갈 거야'라고","link":"https://v.daum.net/v/20240831233527675","retrieved":1725117186482},{"title":"장나라X유나, 지승현 빈자리에 오열 \"아빠가 미운데 보고 싶어\" (다음 연예 ─ 뉴스 ─ 드라마)","contents":"[텐아시아=조나연 기자] 차은경(장나라 분)과 김재희(유나 분)이 김지상(지승현 분)의 빈자리를 크게 느꼈다.&nbsp; 31일 방송된 SBS '굿파트너'에서는 차은경이 이혼 소송을 마친 후 다시 위기에 봉착한 모습이 그려졌다.&nbsp; 오대규(정재성 분)은 차은경에게 \"차변이 이혼 팀에 꼭 필요한지, 젊은 사람들이 결혼도 안 한 세상에 이혼 팀을 굳이 독립적인 팀으로","link":"https://v.daum.net/v/20240831232106543","retrieved":1725117186483},{"title":"“어른이 된다는 것의 의미” 윤여정, 손석희 첫인상 ‘깎은 밤톨같아’ (다음 연예 ─ 뉴스 ─ 예능)","contents":"윤여정이 손석희의 특별한 인연을 회상하며 방송 출연한 이유를 밝혔다. 지난 31일 방송된 MBC 특집 프로그램 ‘손석희의 질문들’ 5회에서는 ‘어른이 된다는 것의 의미’를 주제로 깊이 있는 대화가 이어졌다. 이번 방송의 특별 게스트로는 배우 윤여정이 출연해 눈길을 끌었다. 손석희는 윤여정을 소개하며 “이번 주제를 정하자마자 떠오른 분은 오직 한 분이었다”며","link":"https://v.daum.net/v/20240901071201734","retrieved":1725142394717},{"title":"'불후' 라키, 2NE1 무대 찢었다..2024 왕중왕전 우승 6.7% (다음 연예 ─ 뉴스 ─ 예능)","contents":"[스타뉴스 | 윤상근 기자] /사진=KBS 2TV '불후의 명곡' '불후의 명곡' 라키가 또 이겼다. 베베의 손을 잡은 라키는 승률 100%의 지켜내며 '불후의 명곡' 대기록을 써냈다. 그야말로 '불후의 남자'가 된 라키다. 8월 31일 방송된 KBS 2TV '불후의 명곡' 670회는 '2024 상반기 왕중왕전' 2부로 리베란테, 정동하X알리, 손태진X신","link":"https://v.daum.net/v/20240901071103723","retrieved":1725142394717},{"title":"♥여친 '집 데이트' 딱 걸린 김종민..유재석 \"결혼식 초대해라\" (다음 연예 ─ 뉴스 ─ 예능)","contents":"[스타뉴스 | 정은채 기자] /사진='놀면 뭐하니?' 방송화면 캡쳐'놀면 뭐 하니?'에서 방송인 유재석이 그룹 코요태 멤버 김종민에게 결혼 초대를 요청했다. 8월 31일 방송된 MBC '놀면 뭐 하니?'에서는 특별 게스트 딘딘과 함께 늦은 여름 휴가를 떠나는 멤버들의 모습이 그려졌다. 이날 멤버들은 여행 크리에이터 곽튜브의 추천을 받아 누룽지 백숙집에","link":"https://v.daum.net/v/20240901070152614","retrieved":1725142394718},{"title":"'전참시' 한상보, 직원 이혼 적극 권장 \"이혼 축하금 200만원+2주 휴가\" (다음 연예 ─ 뉴스 ─ 예능)","contents":"[스타뉴스 | 정은채 기자] /사진='전지적 참견 시점' 방송화면 캡쳐'전지적 참견 시점'에서 탈모 전문가 한상보가 이혼을 적극 권장했다. 8월 31일 밤 방송된 MBC 예능 프로그램 '전지적 참견 시점'(이하 '전참시') 311회에서는 참견인으로 배우 이상엽과 '탈모 신(神)'으로 불리는 의사 한상보가 출연했다. 이날 한상보는 스튜디오에 진찰 도구를","link":"https://v.daum.net/v/20240901070139603","retrieved":1725142394720},{"title":"이미주 \"♥송범근과 서먹? 노코멘트\"→ 유재석 \"♥나경은과 키스 자주 해\" (다음 연예 ─ 뉴스 ─ 예능)","contents":"(엑스포츠뉴스 윤채현 기자) 가수 겸 방송인 이미주가 진실 게임에서&nbsp;노코멘트를 택했다. 31일 방송된 MBC '놀면 뭐하니?(이하 '놀뭐')'에서는 'MZ 게임'이라는 이름 아래 랜덤 질문을 뽑아 답을 하는 진실게임이 진행됐다. 이날 유재석은 '마지막 키스가 한 달 안에 있다? 없다?'라는 질문에 대답 대신 청양고추를 먹으며 \"전 자주한다\"라고 답해 사랑꾼","link":"https://v.daum.net/v/20240901065151515","retrieved":1725142394722},{"title":"이준, 집 급습에 혼비백산…잠입 도운 매니저도 당황 (다음 연예 ─ 뉴스 ─ 예능)","contents":"[마이데일리 = 박서연 기자] '1박 2일' 멤버들이 새 식구 이준의 집을 깜짝 습격한다. 1일 방송되는 KBS 2TV 예능프로그램 '1박 2일 시즌4'(이하 '1박 2일')에서는 새 멤버 이준의 집을 기습 방문하는 '1박 2일' 팀의 이야기가 그려진다. 촬영 당일 아침 일찍부터 모인 제작진과 김종민, 문세윤, 딘딘, 유선호는 '1박 2일'의 새 멤버","link":"https://v.daum.net/v/20240901062451379","retrieved":1725142394724},{"title":"'카드값 月 2000만' 한상보, 독특한 직원 복지 \"이혼 축하금 200만원 + 2주 휴가\" (다음 연예 ─ 뉴스 ─ 예능)","contents":"(엑스포츠뉴스 이창규 기자)&nbsp;탈모 전문의 한상보가 병원의 복지에 대해 언급했다. 31일 방송된 MBC '전지적 참견 시점'에서는 한상보가 병원에 출근해서 직원들과 일과를 준비하는 과정이 그려졌다. 이날 한상보는 머리를 세팅한 뒤 지갑에서 돈을 꺼내 매니저에게 \"천 원 깎아줘\"라고 말했는데, 매니저는 안된다면서 돈을 받아갔다. 매니저는 \"(평소에) 먼저 '오","link":"https://v.daum.net/v/20240901062151366","retrieved":1725142394727},{"title":"최선규 “출산한 아내, 자다가 추워서 창가로 밀어” 충격 (다음 연예 ─ 뉴스 ─ 예능)","contents":"최선규 아나운서가 출산한 아내와 에피소드를 밝혀 모두를 놀라게 했다. 8월 31일 방송된 MBN ‘속풀이쇼 동치미’에서는 최선규 아나운서가 아내가 출산할 당시 저지른 만행을 고백했다. 최선규 아나운서는 “아내가 고향이 광주다. 첫애 임신해서 친정에 갔다. 진통이 와서 병원에 가면 나중에 오라고 이걸 4번을 했다. 내가 숙직을 하고 다음 날 출산한다고","link":"https://v.daum.net/v/20240901060853242","retrieved":1725138683290},{"title":"백수련 “100억대 빚, ♥김인태 내 탓 파킨슨병 걸려” (다음 연예 ─ 뉴스 ─ 예능)","contents":"배우 백수련이 100억대 빚을 고백하며 남편의 파킨슨병도 제 탓을 했다. 8월 31일 방송된 MBN ‘속풀이쇼 동치미’에서 배우 백수련은 “나 때문에 우리 남편이 파킨슨병에 걸렸다”는 제목으로 속풀이를 했다. 백수련 남편은 배우 김인태. 백수련은 “사고를 많이 저지르는 여자다. 생각보다 덤벙대고. 남 말을 잘 듣는 편이다. 50년대 후반에 연기를 시작","link":"https://v.daum.net/v/20240901060801236","retrieved":1725138683295},{"title":"이태곤 “눈여겨보는 친구 있어” 파격 연애 고백? (다음 연예 ─ 뉴스 ─ 예능)","contents":"이태곤이 눈여겨보는 사람이 있다고 말했다. 8월 31일 방송된 KBS 2TV ‘살림하는 남자들’에서는 배우 이태곤이 선배 최재성과 만나 파격 고백을 예고했다. 이날 방송말미 예고편에서는 배우 이태곤이 선배 배우 최재성을 만나는 모습이 그려졌다. 최재성은 이태곤에게 “넌 언제 결혼할 거냐. 너한테 어울리는 스타일은 어떤 스타일이냐”고 결혼 계획과 이상형","link":"https://v.daum.net/v/20240901060757235","retrieved":1725138683296},{"title":"이민우 母, 치매 실종 예방 목걸이→박서진 선물로 치유 (다음 연예 ─ 뉴스 ─ 예능)","contents":"이민우 모친이 치매 실종 예방 목걸이로 분노했던 마음을 박서진의 목걸이 선물로 치유했다. 8월 31일 방송된 KBS 2TV ‘살림하는 남자들’에서 가수 박서진은 신화 이민우 모친에게 목걸이를 선물했다. 박서진은 자신의 팬인 이민우 모친이 ‘살림남’ 대표로 ‘전국노래자랑’에 나간다는 소식을 듣고 장구를 가르쳐 드렸다. 이어 박서진은 “저번에 방송을 봤다","link":"https://v.daum.net/v/20240901060754234","retrieved":1725138683296},{"title":"최선규 “기러기 20년, 본처 보내고 젊은 여자와 살림 소문나” (다음 연예 ─ 뉴스 ─ 예능)","contents":"최선규 아나운서가 헛소문을 토로했다. 8월 31일 방송된 MBN ‘속풀이쇼 동치미’에서 최선규 아나운서는 20년을 기러기 아빠로 살았다고 밝혔다. 최선규는 “기러기 생활 20년 하면 오해를 많이 받는다. 본처와 애들은 캐나다에 보내놓고 젊은 여자와 살림 차려 아들딸 낳고 뻔뻔하게 같이 교회를 다닌다고 하더라”고 자신을 둘러싼 헛소문을 밝혔다. 최은경","link":"https://v.daum.net/v/20240901060746233","retrieved":1725138683298},{"title":"최선규 “민통선 땅 3만평 사기, 통일 전까지 세금 안 나와” (다음 연예 ─ 뉴스 ─ 예능)","contents":"최선규가 민간인출입통제구역에 땅이 3만평 있다고 밝혔다. 8월 31일 방송된 MBN ‘속풀이쇼 동치미’에서 최선규 아나운서는 기획부동산에 제대로 당한 이야기를 털어놨다. 최선규 아나운서는 “전국에 나만큼 땅이 많은 사람 나와 보라고 해라. 땅 필요하냐. 줄 테니까 알아서 써라”며 기획 부동산에 당해 민간인출입통제구역에 있는 맹지 3만평을 샀다고 말했다","link":"https://v.daum.net/v/20240901060736230","retrieved":1725138683300},{"title":"박서진, 母도 경악한 홍지윤과 핑크빛 무드 “시집오라 해라” (다음 연예 ─ 뉴스 ─ 예능)","contents":"박서진과 홍지윤의 핑크빛 무드에 가족들이 더 신났다. 8월 31일 방송된 KBS 2TV ‘살림하는 남자들’에서는 가수 박서진 가족이 문경 여행을 떠났다. 박서진은 “봄에 가족 여행을 구례로 떠났다. 부모님이 좋아하셨다. 문경에서 체육대회를 했는데 아빠도 왔으면 아쉬워서. 제가 문경 홍보대사라 볼거리도 먹을거리도 많아 여행 계획을 짰다”고 말했다. 이","link":"https://v.daum.net/v/20240901060704220","retrieved":1725138683303},{"title":"박서진, 12㎏ 감량 여동생 머리크기 공격 “더 큰 건 없나?” (다음 연예 ─ 뉴스 ─ 예능)","contents":"박서진이 남매가 티격태격 케미를 보였다. 8월 31일 방송된 KBS 2TV ‘살림하는 남자들’에서 가수 박서진은 여동생 박효정을 끊임없이 놀렸다. 이날 방송에서는 가수 박서진 가족이 문경으로 놀러간 모습이 그려졌다. 박서진은 아침부터 배고프다는 여동생을 “살 안 빼냐”며 놀렸다. 앞서 박서진 동생은 20kg을 빼기로 약속했고 현재 12kg을 감량한 상","link":"https://v.daum.net/v/20240901060659218","retrieved":1725138683313},{"title":"트와이스 정연 \"활동 쉴때 친구 카페 알바 했다\" 안타까운 고백 (다음 연예 ─ 뉴스 ─ 스타)","contents":"[스타뉴스 | 윤상근 기자] /사진=유튜브 '감별사'/사진=유튜브 '감별사'/사진=유튜브 '감별사' 트와이스 정연이 활동 중단 당시 카페에서 알바를 했던 비하인드를 털어놓았다. 정연은 8월 31일 유튜브 '감별사'에서 공개된 '강남 집 털러 갔는데 상화 물건만 잔뜩 받았다고?! 최초로 부부 애장품 받아봤습니다!'라는 제목의 영상에 등장해 강남과 이야기를","link":"https://v.daum.net/v/20240901070710694","retrieved":1725142399292},{"title":"‘완벽한 가족’ 김병철·윤세아→박주현까지! 휘몰아치는 연기 열전 (다음 연예 ─ 뉴스 ─ 스타)","contents":"‘완벽한 가족’이 튼튼한 팀워크가 돋보이는 5, 6회 비하인드 영상을 공개했다. 지난 달 28일과 29일에 방송된 KBS 2TV 수목드라마 ‘완벽한 가족’(제작 빅토리콘텐츠/ⓒ함창석, 주은/대원씨아이) 5, 6회에서는 최선희(박주현 분)가 연이어 교통사고를 당한 가운데, 누군가 의도적으로 사고를 낸 정황이 드러나며 숨 막히는 긴장감을 선사했다. 공개","link":"https://v.daum.net/v/20240901070339659","retrieved":1725142399292},{"title":"'미녀와 순정남' 고윤은 임수향의 정체를 눈치챌까 (다음 연예 ─ 뉴스 ─ 스타)","contents":"[티브이데일리 김진석 기자] '미녀와 순정남' 고윤이 임수향의 정체를 눈치챌 수 있을까. 지난 8월 31일 저녁 방송된 KBS2 주말드라마 '미녀와 순정남'(극본 김사경·연출 홍석구) 43회에선 공진단(고윤)이 박도라·김지영(임수향)의 정체에 대해 고민하는 장면이 방송됐다. 이날 공진단은 고필승(지현우)에게 맞은 것을 떠올리며 \"몇 번을 얻어터지는 거야","link":"https://v.daum.net/v/20240901070328654","retrieved":1725142399297},{"title":"50대의 우아함 김지호... “자연스러움 속 빛나는 세련미” (다음 연예 ─ 뉴스 ─ 스타)","contents":"김지호가 오프숄더 패션과 노메이크업으로 당당한 매력을 발산했다. 배우 김지호가 31일 자신의 SNS 채널을 통해 근황을 전하며 팬들과 소통했다. 이날 김지호는 “단발 커트, 노메이크업, 뭐선 자신감? 그래도 당당하고 싶다. 핫도그, 나 고딩 때 원디스 먹던 기억... 콜라 맛을 알아버렸다, 큰일이다”라는 해시태그와 함께 유쾌한 일상을 공개했다. 꾸밈없는 자","link":"https://v.daum.net/v/20240901070302641","retrieved":1725142399297},{"title":"'굿파트너' 유나, 장나라에 \"父 지승현, 너무 미운데 너무 보고싶어\" 오열 (다음 연예 ─ 뉴스 ─ 스타)","contents":"[스포츠투데이 백지연 기자] '굿파트너' 장나라가 유나에게 사과했다. 31일 밤 방송된 SBS 예능프로그램 '굿파트너'에서 차은경(장나라)이 김재희(유나)를 위로하려고 노력했다. 이날 차은경은 김재희와 함께 나들이에 나섰다. 아빠 김지상(지승현)의 빈자리를 느끼게 하지 않으려고 노력했지만 역부족이었다. 함께 타는 자전거를 타다가 사고를 냈고 딸의 다리","link":"https://v.daum.net/v/20240901070230629","retrieved":1725142399299},{"title":"'찬또배기' 이찬원, '수은등' 무대 100만 뷰 돌파…남다른 인기 (다음 연예 ─ 뉴스 ─ 스타)","contents":"(엑스포츠뉴스 이정범 기자) 이찬원의 '수은등' 영상이 유튜브 조회수 100만 뷰를 넘어섰다.&nbsp; 2023년 11월 25일 이찬원의 공식 유튜브채널(일명 또튜브)에는 \"수은등 [불후의 명곡 2 전설을 노래하다/ Immortal Songs 2]\"라는 제목의 영상이 게재됐다.&nbsp; 영상 속에는 '불후의 명곡 in US 특집' 편 이찬원의 '수은등' 무대가 담겨 있다","link":"https://v.daum.net/v/20240901070152613","retrieved":1725142399299},{"title":"태양, 7년간 지지 않았네…'빅뱅 이론' 다시 태통하나 (다음 연예 ─ 뉴스 ─ 스타)","contents":"[서울=뉴시스]이재훈 기자 = 태양은 지지 않는다. 8월31일 서울 송파구 올림픽공원 올림픽홀에서 펼쳐진 '태양 2024 투어 더 라이트 이어(THE LIGHT YEAR) 인 서울' 무대에 오른 그룹 '빅뱅' 멤버 겸 솔로 가수 태양(동영배·36)은 여전히 눈부셨다. 그룹 활동을 한창 할 때부터 실력 있는 솔로 아이돌로 입소문 났던 그는 7년 만에 연","link":"https://v.daum.net/v/20240901070138602","retrieved":1725142399299},{"title":"윤여정 \"나도 '난민' 출신..리본 달았다고 정치적?\" 일갈 (다음 연예 ─ 뉴스 ─ 스타)","contents":"[스타뉴스 | 김나라 기자] 윤여정 /사진=MBC '손석희의 질문들' 캡처'손석희의 질문들'에 출연한 윤여정배우 윤여정이 '손석희의 질문들'에서 특유의 돌직구 화법으로 시청자들을 사로잡았다. 윤여정은 8월 31일 오후 방송된 MBC '손석희의 질문들' 5회 게스트로 등장, 프로그램의 마지막을 장식했다. 이날 윤여정은 2021년 영화 '미나리'로 제93회","link":"https://v.daum.net/v/20240901070131596","retrieved":1725142399299},{"title":"김용만 \"이혼하고 싶었던 순간 있었다\" (다음 연예 ─ 뉴스 ─ 스타)","contents":"[서울=뉴시스] 신효령 기자 = '한 번쯤 이혼할 결심'의 MC 김용만이 이혼을 생각한 순간이 있었다고 털어놨다. 1일 오후 10시 방송되는 MBN '한 번쯤 이혼할 결심'에서는 '결혼 46년 차' 이혜정 고민환 부부가 MC 김용만을 비롯해 절친한 지인들을 집으로 초대해 바비큐 홈파티를 즐긴다. 이혜정은 과천 집의 마당에 바비큐 세팅을 해놓은 뒤, 직","link":"https://v.daum.net/v/20240901070112583","retrieved":1725142399300},{"title":"윤여정 \"배우로서 잘 늙는다는 것은\" 명문 파티 (다음 연예 ─ 뉴스 ─ 스타)","contents":"[OSEN=오세진 기자] ‘손석희의 질문들’ 배우 윤여정이 자신만의 독특한 철학을 내보였다. 31일 방영한 MBC 시사교양 프로그램 ‘손석희의 질문들’에서는 배우 윤여정이 출연했다.&nbsp;손석희는 “마지막 질문이다. 설렘이 더 커서 서운함이 생각나지 않았다. 주제는 ‘어른이 된다는 것’이다. 주제를 잡자마자 그 어른만이 생각 났다. 바로 윤여정이다”라며 윤여","link":"https://v.daum.net/v/20240901070001535","retrieved":1725142399300},{"title":"전종서, ‘황금 골반’은 숨길 수가 없어! 숨 막히는 S라인 딱붙핏 드레스룩 (다음 연예 ─ 뉴스 ─ 스타)","contents":"전종서가 숨 막히는 S라인 딱붙핏 드레스룩을 선보였다. 배우 전종서가 최근 패션 매거진 ‘엘르’와의 화보 촬영을 통해 독보적인 매력을 선보였다. 이번 화보는 ‘전종서의 밤’을 주제로, 달빛 아래서 그녀의 고요하면서도 신비로운 매력을 담아낸 것이 특징이다. 화보 속 전종서는 플라워 패턴이 돋보이는 오프숄더 탑을 착용하며 화사하고 산뜻한 분위기를 자아냈다. 그","link":"https://v.daum.net/v/20240901065700526","retrieved":1725142399301},{"title":"\"부기 장난 아니죠?\" 이다은, 둘째 낳고 살 더 쪘네..어떤 모습? (다음 연예 ─ 뉴스 ─ 스타)","contents":"[스타뉴스 | 윤상근 기자] /사진=유튜브 '남다리맥' '돌싱글즈2' 이다은이 출산 이후 체중이 늘어난 근황을 전했다. 이다은은 8월 30일 유튜브 '남다리맥'을 통해 산후조리원 일상을 담은 영상을 공개했다. 영상에서 이다은은 \"둘째 임신하고 나서 24kg 정도 살이 쪘다. 리은이 때는 19kg 정도 쪘다. 이번에 훨씬 더 많이 쪘다\"라고 말했다. 직","link":"https://v.daum.net/v/20240901065610522","retrieved":1725142399302},{"title":"♥남궁민 이러니 반했지..진아름 \"멋지고 존경\" 본업 열일 '포착' (다음 연예 ─ 뉴스 ─ 스타)","contents":"[스타뉴스 | 윤상근 기자] /사진=진아름 모델 출신 배우 진아름이 본업 열일 근황을 전했다. 진아름은 8월 31일 \"예쁘고 사랑스럽고 멋진 모델 후배님들과. 오랜만에 무대에 오르니 즐겁기도 했고, 무대 한 번을 위해 많은 사람들의 수많은 노력들이 있었단 걸 알기에 모두가 멋지고 존경스러웠습니다. 보이지 않는 곳에서 많이 애써주신 스탭 여러분 고생하셨구","link":"https://v.daum.net/v/20240901064328495","retrieved":1725142399305},{"title":"'120억 FLEX' 장윤정, ♥도경완 주책에 \"하늘이 주신 재능\" 헛웃음 (다음 연예 ─ 뉴스 ─ 스타)","contents":"(엑스포츠뉴스 이창규 기자)&nbsp;가수 장윤정이 주방을 공개한 가운데, 도경완의 주접이 눈길을 끈다. 지난 30일 유튜브 채널 '도장TV'에는 '시어머님께 배운 도.둑.질 (aka 밥도둑 혹은 시어머니 레시피)'라는 제목의 영상이 게재됐다. 공개된 영상에서 장윤정은 \"요새 입맛이 없어서 살이 좀 빠졌다\"면서 더운 여름에 입맛을 살릴 수 있는 메뉴에 대해 이야기를","link":"https://v.daum.net/v/20240901064002483","retrieved":1725142399307},{"title":"'육즙수지' 이수지, 과즙세연·방 의장 패러디 (다음 연예 ─ 뉴스 ─ 스타)","contents":"[서울=뉴시스]이재훈 기자 = 코미디언 이수지와 김규원이 국내 동영상 플랫폼(OTT) 쿠팡플레이 예능물 'SNL 코리아' 시즌6를 통해 미국 로스앤젤레스(LA) 베벌리힐스 거리에서 함께 포착된 BJ과즙세연·방시혁 하이브 의장 모습을 패러디했다. 8월31일 공개된 'SNL 코리아 6' 1회 도중 호스트 배우 전종서가 첫 코너 '유토짱 키우기: 한일커플 브이","link":"https://v.daum.net/v/20240901063543469","retrieved":1725142399310},{"title":"어둠 밝히는 '얼굴천재' 차은우, \"헬로 홍콩\" (다음 연예 ─ 뉴스 ─ 해외)","contents":"[마이데일리 = 조성경 기자] 그룹 아스트로 멤버 겸 배우 차은우가 어둠을 밝히는 매력으로 눈길을 사로잡았다. 차은우는 1일 새벽 자신의 SNS 계정을 통해 “Hey, hello hk(홍콩)”이라는 인사말과 함께 지난달 말 홍콩에서 진행된 행사 사진과 더불어 홍콩에서 찍은 사진을 여러 장 공개했다. 특히 홍콩 야경을 배경으로 하는 사진 속 차은","link":"https://v.daum.net/v/20240901024527327","retrieved":1725128145100},{"title":"日 애니 거장 미야자키 하야오, 아시아의 노벨상 '막사이사이상' 수상자 선정 (다음 연예 ─ 뉴스 ─ 해외)","contents":"[TV리포트=이혜미 기자] 일본 애니메이션의 거장 미야자키 하야오가 아시아의 노벨상으로 불리는 '막사이사이상' 수상자로 선정됐다. 31일 일본 공영 방송 NHK에 따르면 이날 라몬 막사이사이상 재단(RMAF)은 올해의 수상자로 미야자키 감독을 선정했다. 재단은 \"하야오 감독의 작품은 상업적으로 성공했을 뿐만 아니라 인간에 대한 깊은 이해를 표현해 보는 이들","link":"https://v.daum.net/v/20240831202300952","retrieved":1725106919250},{"title":"티켓 한장이 1000만원? 오아시스 15년만 재결합에 암표 기승 (다음 연예 ─ 뉴스 ─ 해외)","contents":"[뉴스엔 이하나 기자] 영국 브릿팝의 전설 록밴드 오아시스가 15년 만에 재결합하는 가운데, 이들의 라이브 투어에 암표가 기승을 부리고 있다. 8월 30일(현지시간) 영국 일간 가디언, BBC 방송은 오아시스 순회공연 티켓이 사전 예약 판매 시작 몇 분 만에 6,000만 파운드(한화 약 1,055만 원)가 넘는 가격에 재판매되기 시작했다고 보도했다.","link":"https://v.daum.net/v/20240831195452689","retrieved":1725102624465},{"title":"안젤리나 졸리 “2년뒤 LA 떠나 캄보디아로 이사가겠다”, 공식 발표 (다음 연예 ─ 뉴스 ─ 해외)","contents":"[마이데일리 = 곽명동 기자]할리우드 배우 안젤리나 졸리(49)가 LA를 떠나겠다고 밝혔다. 그는 30일(현지시간) 할리우드 리포터와 인터뷰에서 “나는 이 도시에서 자랐고 브래드 피트와 이혼으로 인해 이곳에 있어야 한다”고 말했다. 이어 “현재 16살인 막내 녹스와 비비안이 18살이 되면 곧 떠날 수 있을 것”이라면서 “대가족이 생기면 프라이버시,","link":"https://v.daum.net/v/20240831150727560","retrieved":1725084988865},{"title":"'37세' 유역비, 스모키 화장+망사 스타킹...남심 제대로 강타 (다음 연예 ─ 뉴스 ─ 해외)","contents":"[TV리포트=강성훈 기자] 중국 배우 유역비(37)가 과감한 변신을 시도해 이목이 쏠린다. 최근 유역비는 자신의 사진 몇 장을 올렸다. 사진 속에서 유역비는 진한 스모키 화장에 망사 스타킹을 입은 채로 드럼을 치고 있었다. 평소와는 다른 과감한 모습에 팬은 놀라움을 금치 못했다. 이들은 \"사진 정말 놀랍다\", \"유역비 왜 이렇게 예쁘냐\", \"새로운 매력\"","link":"https://v.daum.net/v/20240831140030925","retrieved":1725081192578},{"title":"日 인기 아이돌 AKB48 멤버, 11년 만에 팀 떠난다... (다음 연예 ─ 뉴스 ─ 해외)","contents":"[TV리포트=전하나 기자] 일본 인기 아이돌 그룹 AKB48 멤버 코미야마 하루카(25)가 그룹 활동 11년 만에 졸업을 발표해 이목을 끈다. 30일(현지 시간), 코미야마 하루카가 도쿄 아키하바라의 AKB 극장에서 개최된 '나의 태양' 공연에서 AKB48 졸업을 발표했다. 코미야마는 지난 2013년 연구생 공연으로 데뷔했으며, 11년 간 활동 끝에 아이돌","link":"https://v.daum.net/v/20240831135830899","retrieved":1725081192578},{"title":"'매튜 페리 사망 사건' 연루 의사, 유죄 인정 동의 (다음 연예 ─ 뉴스 ─ 해외)","contents":"[TV리포트=강성훈 기자] 고(故) 매튜 페리(향년 54세) 사망 사건에 연루된 의사가 유죄를 인정하기로 동/ 사진=의했다. 31일(현지 시간) 외신 'Kxan'는 메튜 페리의 사망과 관련해 기소된 두 의사 중 한 명이 로스앤젤레스 연방법원에 출석했다고 보도했다. 보도에 따르면 부패한 의사는 수술용 마취제 케타민을 배포한 공모 혐의에 대해 유죄를 인정하고","link":"https://v.daum.net/v/20240831125600329","retrieved":1725077779816},{"title":"“안젤리나 졸리 열받을 듯” 브래드 피트, 여친과 프랑스 포도밭서 휴가 보내 (다음 연예 ─ 뉴스 ─ 해외)","contents":"[마이데일리 = 곽명동 기자]할리우드 배우 브래드 피트(60)가 여 보석 디자이너 이네스 드 라몬(34)과 프랑스 와이너리 샤토 미라발에서 여름 휴가를 보냈다. 피트와 소유권을 둘러싸고 치열한 소송을 벌이고 있는 전 부인 안젤리나 졸리(49) 입장에선 화가 날 만한 상황이다. 30(현지시) 페이지식스에 따르면, 피트는 샤토 미라발 외에도 이탈리아 쿠오모","link":"https://v.daum.net/v/20240831123728207","retrieved":1725077779817},{"title":"앤젤리나 졸리, 아픈 팬 위해…레드카펫서 무릎 꿇고 눈맞춤 (다음 연예 ─ 뉴스 ─ 해외)","contents":"(서울=뉴스1) 고승아 기자 = 할리우드 배우 앤젤리나 졸리(안젤리나 졸리)가 레드카펫에서 팬과 특별한 만남을 가졌다. 미국 연예매체 스플래시닷컴은 지난 29일(현지시간) 이탈리아 베니스 리도섬에서 열린 제81회 베니스국제영화제 영화 '마리아' 레드카펫에 참석한 졸리의 사진을 공개했다. 공개된 사진 속 졸리는 베이지 톤의 드레스에 퍼 재킷을 걸친 채 어","link":"https://v.daum.net/v/20240831123044170","retrieved":1725077779818},{"title":"갤러거 형제, 프랑스서 비밀리 재회→오아시스 '재결합' 투어 사전티켓 매진 (다음 연예 ─ 뉴스 ─ 해외)","contents":"[TV리포트=강성훈 기자] 재결합한 밴드 그룹 오아시스의 갤러거 형제에 관한 관심이 뜨겁다. 30일(현지 시간) 외신 '더 선'은 형인 노엘 갤러거(57)가 동생 리암 갤러거(51)를 만나기 위해 프랑스로 갈 예정이라고 보도했다. 보도에 따르면 한 소식통은 \"(두 사람의 어머니) 페기 갤러거(81)는 10년 이상 말을 하지 않은 두 아들이 화해해서 매우 기","link":"https://v.daum.net/v/20240831122531147","retrieved":1725077779825},{"title":"티모시 샬라메, 밥 딜런 변신 포스터 공개 \"압박감 커..팬들이 찢어버릴 것\" (다음 연예 ─ 뉴스 ─ 해외)","contents":"[OSEN=최이정 기자]&nbsp;배우 티모시 샬라메(28)가 전설의 뮤지션 밥 딜런으로 변신한 새 영화 'A Complete Unknown'의 첫 공식 포스터를 공유했다.&nbsp; 샬라메는 30일(현지시간) 자신의 소셜미디어계정에 해당 포스터를&nbsp;게재하며&nbsp;'INCOMING'이라는 글을 덧붙였다.&nbsp; 포스터 속 샬라메는 검은색 선글라스, 줄무늬 단추 셔츠, 어두운 블레이저","link":"https://v.daum.net/v/20240831114430831","retrieved":1725074033564},{"title":"안젤리나 졸리, 래퍼 아킬라와 베니스 호텔서 포착…\"친구일 뿐\" (다음 연예 ─ 뉴스 ─ 해외)","contents":"안젤리나 졸리와 아킬라. /사진=피플(뉴시스)할리우드 배우 안젤리나 졸리(49)가 최근 두 차례의 열애설에 휩싸였으나 모두 \"친구 사이일 뿐\"이라며 부인했다. 29일(현지 시각) 외신 피플에 따르면 졸리는 래퍼 아킬라와 베니스의 한 호텔에서 함께 있는 모습이 포착되면서 열애설에 휘말렸다. 하지만 관계자들은 \"두 사람은 연인 관계가 아니다\"라며 \"아킬라의","link":"https://v.daum.net/v/20240831113331748","retrieved":1725074033564},{"title":"정호연, 케이트 블란쳇과 강렬한 투샷 “베니스영화제 환호” (다음 연예 ─ 뉴스 ─ 해외)","contents":"[마이데일리 = 곽명동 기자]넷플릭스 ‘오징어게임’으로 유명한 배우 정호연이 베니스를 뜨겁게 달궜다. 정호연은 29일(현지시간) 이탈리아 리도섬에서 열린 제81회 베니스국제영화제에 참석해 레드카펫을 밟았다. 그는 애플TV+ '누군가는 알고 있다(원제:Disclaimer)'의 프리미어 시사회를 위해 베니스영화제에 모습을 드러냈다. '누군가는 알고 있다","link":"https://v.daum.net/v/20240831105851378","retrieved":1725070166419}]}